{
  "Presets": [
    {
      "Name": "StoryHoloGram_Common",
      "OverrideReplaceMaterialKeyList": [
        "StoryHoloGram_Common"
      ],
      "SFXOnLoad": "Ev_sfx_npc_common_projection_loop"
    },
    {
      "Name": "StoryHoloGram_Special_Common",
      "OverrideReplaceMaterialKeyList": [
        "StoryHoloGram_Special_Common"
      ],
      "SFXOnLoad": "Ev_sfx_npc_common_projection_loop"
    },
    {
      "Name": "StoryHoloGram_OnlyItem",
      "OverrideReplaceMaterialKeyList": [
        "StoryHoloGram_OnlyItem"
      ],
      "SFXOnLoad": "Ev_sfx_npc_common_projection_loop"
    },
    {
      "Name": "StoryHoloGram_HoLai",
      "OverrideReplaceMaterialKeyList": [
        "StoryHoloGram_HoLai"
      ],
      "SFXOnLoad": "Ev_sfx_npc_common_projection_loop"
    },
    {
      "Name": "Aventurine_00_Phantom",
      "OverrideReplaceMaterialKeyList": [
        "Aventurine_00_Phantom"
      ],
      "SFXOnLoad": "Ev_sfx_npc_common_projection_loop"
    },
    {
      "Name": "Yukong_00_Phantom",
      "OverrideReplaceMaterialKeyList": [
        "Yukong_00_Phantom"
      ],
      "SFXOnLoad": "Ev_sfx_npc_common_projection_loop"
    },
    {
      "Name": "Silwolf_00_Phantom",
      "OverrideReplaceMaterialKeyList": [
        "Silwolf_00_Phantom"
      ],
      "SFXOnLoad": "Ev_sfx_npc_common_projection_loop"
    },
    {
      "Name": "Rappa_00_Phantom",
      "OverrideReplaceMaterialKeyList": [
        "Rappa_00_Phantom"
      ],
      "SFXOnLoad": "Ev_sfx_npc_common_projection_loop"
    },
    {
      "Name": "Tingyun_00_Phantom",
      "OverrideReplaceMaterialKeyList": [
        "Tingyun_00_Phantom"
      ],
      "SFXOnLoad": "Ev_sfx_npc_common_projection_loop"
    },
    {
      "Name": "Mr_Reca_00_Phantom",
      "OverrideReplaceMaterialKeyList": [
        "Mr_Reca_00_Phantom"
      ],
      "SFXOnLoad": "Ev_sfx_npc_common_projection_loop"
    },
    {
      "Name": "Screwllum_00_Phantom",
      "OverrideReplaceMaterialKeyList": [
        "Screwllum_00_Phantom"
      ],
      "SFXOnLoad": "Ev_sfx_npc_common_projection_loop"
    },
    {
      "Name": "Sunday_00_Phantom",
      "OverrideReplaceMaterialKeyList": [
        "Sunday_00_Phantom"
      ],
      "SFXOnLoad": "Ev_sfx_npc_common_projection_loop"
    },
    {
      "Name": "Firefly_00_Phantom",
      "OverrideReplaceMaterialKeyList": [
        "Firefly_00_Phantom"
      ],
      "SFXOnLoad": "Ev_sfx_npc_common_projection_loop"
    },
    {
      "Name": "TheHerta_00_Phantom",
      "OverrideReplaceMaterialKeyList": [
        "TheHerta_00_Phantom"
      ],
      "SFXOnLoad": "Ev_sfx_npc_common_projection_loop"
    },
    {
      "Name": "StoryHoloGram_OrigamiBird_00_Silwolf",
      "OverrideReplaceMaterialKeyList": [
        "StoryHoloGram_OrigamiBird_00_Silwolf"
      ],
      "SFXOnLoad": "Ev_sfx_npc_common_projection_loop"
    },
    {
      "Name": "NPC_W2_Lady_24_StoryGhost",
      "OverrideReplaceMaterialKeyList": [
        "NPC_W2_Lady_24_StoryGhost"
      ],
      "SFXOnLoad": "Ev_sfx_npc_common_StoryGhost_loop"
    },
    {
      "Name": "NPC_W2_Child_01_StoryGhost",
      "OverrideReplaceMaterialKeyList": [
        "NPC_W2_Child_01_StoryGhost"
      ],
      "SFXOnLoad": "Ev_sfx_npc_common_StoryGhost_loop"
    },
    {
      "Name": "NPC_W2_Child_03_StoryGhost",
      "OverrideReplaceMaterialKeyList": [
        "NPC_W2_Child_03_StoryGhost"
      ],
      "SFXOnLoad": "Ev_sfx_npc_common_StoryGhost_loop"
    },
    {
      "Name": "NPC_W2_Child_04_StoryGhost",
      "OverrideReplaceMaterialKeyList": [
        "NPC_W2_Child_04_StoryGhost"
      ],
      "SFXOnLoad": "Ev_sfx_npc_common_StoryGhost_loop"
    },
    {
      "Name": "NPC_W2_Male_27_StoryGhost",
      "OverrideReplaceMaterialKeyList": [
        "NPC_W2_Male_27_StoryGhost"
      ],
      "SFXOnLoad": "Ev_sfx_npc_common_StoryGhost_loop"
    },
    {
      "Name": "NPC_W2_Lady_09_StoryGhost",
      "OverrideReplaceMaterialKeyList": [
        "NPC_W2_Lady_09_StoryGhost"
      ],
      "SFXOnLoad": "Ev_sfx_npc_common_StoryGhost_loop"
    },
    {
      "Name": "NPC_W2_Male_08_StoryGhost",
      "OverrideReplaceMaterialKeyList": [
        "NPC_W2_Male_08_StoryGhost"
      ],
      "SFXOnLoad": "Ev_sfx_npc_common_StoryGhost_loop"
    },
    {
      "Name": "NPC_W2_Lady_49_StoryGhost",
      "OverrideReplaceMaterialKeyList": [
        "NPC_W2_Lady_49_StoryGhost"
      ],
      "SFXOnLoad": "Ev_sfx_npc_common_StoryGhost_loop"
    },
    {
      "Name": "NPC_W2_Lady_08_StoryGhost",
      "OverrideReplaceMaterialKeyList": [
        "NPC_W2_Lady_08_StoryGhost"
      ],
      "SFXOnLoad": "Ev_sfx_npc_common_StoryGhost_loop"
    },
    {
      "Name": "StoryFury_Male",
      "OverrideReplaceMaterialKeyList": [
        "StoryFury_Male"
      ],
      "SFXOnLoad": "Ev_sfx_npc_common_StoryFury_loop"
    },
    {
      "Name": "StoryFury_Lady",
      "OverrideReplaceMaterialKeyList": [
        "StoryFury_Lady"
      ],
      "SFXOnLoad": "Ev_sfx_npc_common_StoryFury_loop"
    },
    {
      "Name": "StoryFury_Old",
      "OverrideReplaceMaterialKeyList": [
        "StoryFury_Old"
      ],
      "SFXOnLoad": "Ev_sfx_npc_common_StoryFury_loop"
    },
    {
      "Name": "StoryFury_Child",
      "OverrideReplaceMaterialKeyList": [
        "StoryFury_Child"
      ],
      "SFXOnLoad": "Ev_sfx_npc_common_StoryFury_loop"
    },
    {
      "Name": "StoryFury_MuscleMan",
      "OverrideReplaceMaterialKeyList": [
        "StoryFury_MuscleMan"
      ],
      "SFXOnLoad": "Ev_sfx_npc_common_StoryFury_loop"
    },
    {
      "Name": "StoryFury_MuscleMan_Face_C",
      "OverrideReplaceMaterialKeyList": [
        "StoryFury_MuscleMan_Face_C"
      ],
      "SFXOnLoad": "Ev_sfx_npc_common_StoryFury_loop"
    },
    {
      "Name": "StoryFury_Tribbie_01",
      "OverrideReplaceMaterialKeyList": [
        "StoryFury_Tribbie_01"
      ],
      "SFXOnLoad": "Ev_sfx_npc_common_StoryFury_loop"
    },
    {
      "Name": "StoryFury_Mydeimos_00",
      "OverrideReplaceMaterialKeyList": [
        "StoryFury_Mydeimos_00"
      ],
      "SFXOnLoad": "Ev_sfx_npc_common_StoryFury_loop"
    },
    {
      "Name": "StoryChrysosFury_Tribbie_01",
      "OverrideReplaceMaterialKeyList": [
        "StoryChrysosFury_Tribbie_01"
      ],
      "SFXOnLoad": "Ev_sfx_npc_common_StoryChrysosFury_loop"
    },
    {
      "Name": "StoryChrysosFury_Mydeimos_00",
      "OverrideReplaceMaterialKeyList": [
        "StoryChrysosFury_Mydeimos_00"
      ],
      "SFXOnLoad": "Ev_sfx_npc_common_StoryChrysosFury_loop"
    },
    {
      "Name": "StoryCrystal_Lady",
      "OverrideReplaceMaterialKeyList": [
        "StoryCrystal_Lady"
      ],
      "SFXOnLoad": "Ev_sfx_npc_common_StoryCrystal_loop",
      "AdditiveResidentEffect": [
        {
          "EffectPath": "Effects/Eff_Prefab/Eff_NPC/Normal/Common/Eff_Normal_Lady_Common_StoryCrystal.prefab",
          "AttachPoint": "Root"
        }
      ]
    },
    {
      "Name": "StoryCrystal_Male",
      "OverrideReplaceMaterialKeyList": [
        "StoryCrystal_Male"
      ],
      "SFXOnLoad": "Ev_sfx_npc_common_StoryCrystal_loop",
      "AdditiveResidentEffect": [
        {
          "EffectPath": "Effects/Eff_Prefab/Eff_NPC/Normal/Common/Eff_Normal_Male_Common_StoryCrystal.prefab",
          "AttachPoint": "Root"
        }
      ]
    },
    {
      "Name": "StoryCrystal_Child",
      "OverrideReplaceMaterialKeyList": [
        "StoryCrystal_Child"
      ],
      "SFXOnLoad": "Ev_sfx_npc_common_StoryCrystal_loop",
      "AdditiveResidentEffect": [
        {
          "EffectPath": "Effects/Eff_Prefab/Eff_NPC/Normal/Common/Eff_Normal_Child_Common_StoryCrystal.prefab",
          "AttachPoint": "Root"
        }
      ]
    },
    {
      "Name": "StoryCrystal_Old",
      "OverrideReplaceMaterialKeyList": [
        "StoryCrystal_Old"
      ],
      "SFXOnLoad": "Ev_sfx_npc_common_StoryCrystal_loop",
      "AdditiveResidentEffect": [
        {
          "EffectPath": "Effects/Eff_Prefab/Eff_NPC/Normal/Common/Eff_Normal_Old_Common_StoryCrystal.prefab",
          "AttachPoint": "Root"
        }
      ]
    },
    {
      "Name": "StoryCrystal_MuscleMan",
      "OverrideReplaceMaterialKeyList": [
        "StoryCrystal_MuscleMan"
      ],
      "SFXOnLoad": "Ev_sfx_npc_common_StoryCrystal_loop",
      "AdditiveResidentEffect": [
        {
          "EffectPath": "Effects/Eff_Prefab/Eff_NPC/Normal/Common/Eff_Normal_MuscleMan_Common_StoryCrystal.prefab",
          "AttachPoint": "Root"
        }
      ]
    },
    {
      "Name": "StoryCrystal_MuscleMan_Face_C",
      "OverrideReplaceMaterialKeyList": [
        "StoryCrystal_MuscleMan_Face_C"
      ],
      "SFXOnLoad": "Ev_sfx_npc_common_StoryCrystal_loop",
      "AdditiveResidentEffect": [
        {
          "EffectPath": "Effects/Eff_Prefab/Eff_NPC/Normal/Common/Eff_Normal_MuscleMan_Common_StoryCrystal.prefab",
          "AttachPoint": "Root"
        }
      ]
    },
    {
      "Name": "StoryCrystal_Aglaea_00",
      "OverrideReplaceMaterialKeyList": [
        "StoryCrystal_Aglaea_00"
      ],
      "SFXOnLoad": "Ev_sfx_npc_common_StoryCrystal_loop",
      "AdditiveResidentEffect": [
        {
          "EffectPath": "Effects/Eff_Prefab/Eff_NPC/Normal/Common/Eff_Normal_Lady_Common_StoryCrystal.prefab",
          "AttachPoint": "Root"
        }
      ]
    },
    {
      "Name": "StoryCrystal_Castorice_00",
      "OverrideReplaceMaterialKeyList": [
        "StoryCrystal_Castorice_00"
      ],
      "SFXOnLoad": "Ev_sfx_npc_common_StoryCrystal_loop",
      "AdditiveResidentEffect": [
        {
          "EffectPath": "Effects/Eff_Prefab/Eff_NPC/Normal/Common/Eff_Normal_Lady_Common_StoryCrystal.prefab",
          "AttachPoint": "Root"
        }
      ]
    },
    {
      "Name": "StoryCrystal_DanHeng_00",
      "OverrideReplaceMaterialKeyList": [
        "StoryCrystal_DanHeng_00"
      ],
      "SFXOnLoad": "Ev_sfx_npc_common_StoryCrystal_loop",
      "AdditiveResidentEffect": [
        {
          "EffectPath": "Effects/Eff_Prefab/Eff_NPC/Normal/Common/Eff_Normal_Male_Common_StoryCrystal.prefab",
          "AttachPoint": "Root"
        }
      ]
    },
    {
      "Name": "StoryCrystal_Firefly_00",
      "OverrideReplaceMaterialKeyList": [
        "StoryCrystal_Firefly_00"
      ],
      "SFXOnLoad": "Ev_sfx_npc_common_StoryCrystal_loop",
      "AdditiveResidentEffect": [
        {
          "EffectPath": "Effects/Eff_Prefab/Eff_NPC/Normal/Common/Eff_Normal_Lady_Common_StoryCrystal.prefab",
          "AttachPoint": "Root"
        }
      ]
    },
    {
      "Name": "StoryCrystal_Kafka_00",
      "OverrideReplaceMaterialKeyList": [
        "StoryCrystal_Kafka_00"
      ],
      "SFXOnLoad": "Ev_sfx_npc_common_StoryCrystal_loop",
      "AdditiveResidentEffect": [
        {
          "EffectPath": "Effects/Eff_Prefab/Eff_NPC/Normal/Common/Eff_Normal_Lady_Common_StoryCrystal.prefab",
          "AttachPoint": "Root"
        }
      ]
    },
    {
      "Name": "StoryCrystal_Mydeimos_00",
      "OverrideReplaceMaterialKeyList": [
        "StoryCrystal_Mydeimos_00"
      ],
      "SFXOnLoad": "Ev_sfx_npc_common_StoryCrystal_loop",
      "AdditiveResidentEffect": [
        {
          "EffectPath": "Effects/Eff_Prefab/Eff_NPC/Normal/Common/Eff_Normal_Male_Common_StoryCrystal.prefab",
          "AttachPoint": "Root"
        }
      ]
    },
    {
      "Name": "StoryCrystal_Phainon_00",
      "OverrideReplaceMaterialKeyList": [
        "StoryCrystal_Phainon_00"
      ],
      "SFXOnLoad": "Ev_sfx_npc_common_StoryCrystal_loop",
      "AdditiveResidentEffect": [
        {
          "EffectPath": "Effects/Eff_Prefab/Eff_NPC/Normal/Common/Eff_Normal_Male_Common_StoryCrystal.prefab",
          "AttachPoint": "Root"
        }
      ]
    },
    {
      "Name": "StoryCrystal_Ren_00",
      "OverrideReplaceMaterialKeyList": [
        "StoryCrystal_Ren_00"
      ],
      "SFXOnLoad": "Ev_sfx_npc_common_StoryCrystal_loop",
      "AdditiveResidentEffect": [
        {
          "EffectPath": "Effects/Eff_Prefab/Eff_NPC/Normal/Common/Eff_Normal_Male_Common_StoryCrystal.prefab",
          "AttachPoint": "Root"
        }
      ]
    },
    {
      "Name": "StoryCrystal_Silwolf_00",
      "OverrideReplaceMaterialKeyList": [
        "StoryCrystal_Silwolf_00"
      ],
      "SFXOnLoad": "Ev_sfx_npc_common_StoryCrystal_loop",
      "AdditiveResidentEffect": [
        {
          "EffectPath": "Effects/Eff_Prefab/Eff_NPC/Normal/Common/Eff_Normal_Lady_Common_StoryCrystal.prefab",
          "AttachPoint": "Root"
        }
      ]
    },
    {
      "Name": "StoryCrystal_Tribbie_00",
      "OverrideReplaceMaterialKeyList": [
        "StoryCrystal_Tribbie_00"
      ],
      "SFXOnLoad": "Ev_sfx_npc_common_StoryCrystal_loop",
      "AdditiveResidentEffect": [
        {
          "EffectPath": "Effects/Eff_Prefab/Eff_NPC/Normal/Common/Eff_Normal_Child_Common_StoryCrystal.prefab",
          "AttachPoint": "Root"
        }
      ]
    },
    {
      "Name": "StoryCrystal_Tribbie_01",
      "OverrideReplaceMaterialKeyList": [
        "StoryCrystal_Tribbie_01"
      ],
      "SFXOnLoad": "Ev_sfx_npc_common_StoryCrystal_loop",
      "AdditiveResidentEffect": [
        {
          "EffectPath": "Effects/Eff_Prefab/Eff_NPC/Normal/Common/Eff_Normal_Child_Common_StoryCrystal.prefab",
          "AttachPoint": "Root"
        }
      ]
    },
    {
      "Name": "StoryCrystal_Tribbie_02",
      "OverrideReplaceMaterialKeyList": [
        "StoryCrystal_Tribbie_02"
      ],
      "SFXOnLoad": "Ev_sfx_npc_common_StoryCrystal_loop",
      "AdditiveResidentEffect": [
        {
          "EffectPath": "Effects/Eff_Prefab/Eff_NPC/Normal/Common/Eff_Normal_Child_Common_StoryCrystal.prefab",
          "AttachPoint": "Root"
        }
      ]
    },
    {
      "Name": "StoryCrystal_Cipher_00",
      "OverrideReplaceMaterialKeyList": [
        "StoryCrystal_Cipher_00"
      ],
      "SFXOnLoad": "Ev_sfx_npc_common_StoryCrystal_loop",
      "AdditiveResidentEffect": [
        {
          "EffectPath": "Effects/Eff_Prefab/Eff_NPC/Normal/Common/Eff_Normal_Lady_Common_StoryCrystal.prefab",
          "AttachPoint": "Root"
        }
      ]
    },
    {
      "Name": "StoryCrystal_GeoriaSons_00_00",
      "OverrideReplaceMaterialKeyList": [
        "StoryCrystal_GeoriaSons_00_00"
      ],
      "SFXOnLoad": "Ev_sfx_npc_common_StoryCrystal_loop",
      "AdditiveResidentEffect": [
        {
          "EffectPath": "Effects/Eff_Prefab/Eff_NPC/Special/Eff_GeoriaSons_00_StoryCrystal.prefab",
          "AttachPoint": "Root"
        }
      ]
    },
    {
      "Name": "StoryCrystal_PlayerBoy_00",
      "OverrideReplaceMaterialKeyList": [
        "StoryCrystal_PlayerBoy_00"
      ],
      "SFXOnLoad": "Ev_sfx_npc_common_StoryCrystal_loop",
      "AdditiveResidentEffect": [
        {
          "EffectPath": "Effects/Eff_Prefab/Eff_NPC/Normal/Common/Eff_Normal_Male_Common_StoryCrystal.prefab",
          "AttachPoint": "Root"
        }
      ]
    },
    {
      "Name": "StoryCrystal_PlayerGirl_00",
      "OverrideReplaceMaterialKeyList": [
        "StoryCrystal_PlayerGirl_00"
      ],
      "SFXOnLoad": "Ev_sfx_npc_common_StoryCrystal_loop",
      "AdditiveResidentEffect": [
        {
          "EffectPath": "Effects/Eff_Prefab/Eff_NPC/Normal/Common/Eff_Normal_Lady_Common_StoryCrystal.prefab",
          "AttachPoint": "Root"
        }
      ]
    },
    {
      "Name": "StoryCrystal_Anaxa_00",
      "OverrideReplaceMaterialKeyList": [
        "StoryCrystal_Anaxa_00"
      ],
      "SFXOnLoad": "Ev_sfx_npc_common_StoryCrystal_loop",
      "AdditiveResidentEffect": [
        {
          "EffectPath": "Effects/Eff_Prefab/Eff_NPC/Normal/Common/Eff_Normal_Male_Common_StoryCrystal.prefab",
          "AttachPoint": "Root"
        }
      ]
    },
    {
      "Name": "StoryCrystal_W3_Sam_00",
      "OverrideReplaceMaterialKeyList": [
        "StoryCrystal_W3_Sam_00"
      ],
      "SFXOnLoad": "Ev_sfx_npc_common_StoryCrystal_loop",
      "AdditiveResidentEffect": [
        {
          "EffectPath": "Effects/Eff_Prefab/Eff_NPC/Monster/Eff_W3_Sam_00_StoryCrystal.prefab"
        }
      ]
    },
    {
      "Name": "StoryCrystal_W4_FireProwler_00",
      "OverrideReplaceMaterialKeyList": [
        "StoryCrystal_W4_FireProwler_00"
      ],
      "SFXOnLoad": "Ev_sfx_npc_common_StoryCrystal_loop",
      "AdditiveResidentEffect": [
        {
          "EffectPath": "Effects/Eff_Prefab/Eff_NPC/Monster/Eff_W3_FireProwler_00_StoryCrystal.prefab",
          "AttachPoint": "Root"
        }
      ]
    },
    {
      "Name": "StoryCrystal_AML_Minion02_01",
      "OverrideReplaceMaterialKeyList": [
        "StoryCrystal_AML_Minion02_01"
      ],
      "SFXOnLoad": "Ev_sfx_npc_common_StoryCrystal_loop",
      "AdditiveResidentEffect": [
        {
          "EffectPath": "Effects/Eff_Prefab/Eff_NPC/Monster/Eff_W3_Minion02_00_StoryCrystal.prefab",
          "AttachPoint": "Root"
        }
      ]
    },
    {
      "Name": "StoryCrystal_Cerces_00",
      "OverrideReplaceMaterialKeyList": [
        "StoryCrystal_Cerces_00"
      ],
      "SFXOnLoad": "Ev_sfx_npc_common_StoryCrystal_loop",
      "AdditiveResidentEffect": [
        {
          "EffectPath": "Effects/Eff_Prefab/Eff_NPC/Special/Eff_Special_Cerces_00_StoryCrystal.prefab",
          "AttachPoint": "Root"
        }
      ]
    },
    {
      "Name": "StoryCrystal_Pollux_00",
      "OverrideReplaceMaterialKeyList": [
        "StoryCrystal_Pollux_00"
      ],
      "SFXOnLoad": "Ev_sfx_npc_common_StoryCrystal_loop",
      "AdditiveResidentEffect": [
        {
          "EffectPath": "Effects/Eff_Prefab/Eff_NPC/Special/Eff_Special_Pollux_00_StoryCrystal.prefab"
        }
      ]
    },
    {
      "Name": "FeixiaoMind_W2_LycanKing_00",
      "OverrideReplaceMaterialKeyList": [
        "FeixiaoMind_W2_LycanKing_00"
      ],
      "SFXOnLoad": "Ev_sfx_npc_common_FeixiaoMind_loop"
    },
    {
      "Name": "ShaJinYoung_Story01",
      "OverrideReplaceMaterialKeyList": [
        "ShaJinYoung_Story01"
      ]
    }
  ]
}