{
  "OnInitSequece": [
    {
      "TaskList": []
    }
  ],
  "OnStartSequece": [
    {
      "TaskList": [
        {
          "$type": "RPG.GameCore.SetTargetEntityFadeWithAnim",
          "TargetType": {
            "$type": "RPG.GameCore.TargetFetchAdvPropEx",
            "FetchType": "SinglePropByOwnerGroupAndID",
            "PropIDInOwnerGroup": {
              "FixedValue": {
                "Value": 300001
              }
            }
          }
        },
        {
          "$type": "RPG.GameCore.SetTargetEntityFadeWithAnim",
          "TargetType": {
            "$type": "RPG.GameCore.TargetFetchAdvPropEx",
            "FetchType": "SinglePropByOwnerGroupAndID",
            "PropIDInOwnerGroup": {
              "FixedValue": {
                "Value": 300001
              }
            }
          },
          "TargetValue": 1,
          "Duration": 0.3
        }
      ]
    },
    {
      "TaskList": [
        {
          "$type": "RPG.GameCore.SetTargetEntityFadeWithAnim",
          "TargetType": {
            "$type": "RPG.GameCore.TargetFetchAdvPropEx",
            "FetchType": "SinglePropByOwnerGroupAndID",
            "PropIDInOwnerGroup": {
              "FixedValue": {
                "Value": 300002
              }
            }
          }
        },
        {
          "$type": "RPG.GameCore.SetTargetEntityFadeWithAnim",
          "TargetType": {
            "$type": "RPG.GameCore.TargetFetchAdvPropEx",
            "FetchType": "SinglePropByOwnerGroupAndID",
            "PropIDInOwnerGroup": {
              "FixedValue": {
                "Value": 300002
              }
            }
          },
          "TargetValue": 1,
          "Duration": 0.3
        }
      ]
    }
  ],
  "Type": "Group",
  "EntityEventList": []
}