{
  "StateList": [
    {
      "MotionID": 900290000,
      "EntranceFreeStyleIDList": [
        900290367,
        900290201,
        900290368,
        900290371
      ],
      "CanTransitionToState": true
    },
    {
      "MotionID": 900290365,
      "EntranceFreeStyleIDList": [
        900290000
      ]
    },
    {
      "MotionID": 900290366,
      "EntranceFreeStyleIDList": [
        900290365
      ]
    },
    {
      "MotionID": 900290367,
      "EntranceFreeStyleIDList": [
        900290366,
        900290365
      ],
      "CanTransitionToState": true
    },
    {
      "MotionID": 900290201,
      "EntranceFreeStyleIDList": [
        900290000
      ],
      "CanTransitionToState": true
    },
    {
      "MotionID": 900290368,
      "EntranceFreeStyleIDList": [
        900290000
      ],
      "CanTransitionToState": true
    },
    {
      "MotionID": 900290369,
      "EntranceFreeStyleIDList": [
        900290000
      ]
    },
    {
      "MotionID": 900290370,
      "EntranceFreeStyleIDList": [
        900290369
      ]
    },
    {
      "MotionID": 900290371,
      "EntranceFreeStyleIDList": [
        900290370,
        900290369
      ],
      "CanTransitionToState": true
    }
  ]
}