{
  "BakeInfoLayouts": [
    {
      "UniqueName": "MAvatar_Mydeimos_00_Transfer",
      "Offset": 12629,
      "Dependency": [
        "MAvatar_Mydeimos_00_Transfer_LockDEF"
      ]
    },
    {
      "UniqueName": "MAvatar_Mydeimos_00_Transfer_LockDEF",
      "Offset": 15392
    },
    {
      "UniqueName": "MAvatar_Mydeimos_00_SkillTree03",
      "Offset": 15569
    },
    {
      "UniqueName": "Avatar_Mydeimos_00_SkillTree03_Sub",
      "Offset": 15935
    },
    {
      "UniqueName": "MAvatar_Mydeimos_00_Rank02",
      "Offset": 16312
    },
    {
      "UniqueName": "MAvatar_Mydeimos_00_Rank04",
      "Offset": 16956
    },
    {
      "UniqueName": "MAvatar_Mydeimos_00_SkillTree01",
      "Offset": 17239
    },
    {
      "UniqueName": "MAvatar_Mydeimos_00_InsertActionAbortFlag",
      "Offset": 17306
    },
    {
      "UniqueName": "MAvatar_Mydeimos_00_UltraTarget",
      "Offset": 17345
    },
    {
      "UniqueName": "MAvatar_Mydeimos_00_UltraTargetSpecialMark",
      "Offset": 17394
    },
    {
      "UniqueName": "Avatar_Mydeimos_00_Skill22_Predicate",
      "TypeId": "TypeId_TaskListTemplateConfig",
      "Offset": 17787
    },
    {
      "UniqueName": "Avatar_Mydeimos_00_PassiveSkill_Transfer",
      "TypeId": "TypeId_TaskListTemplateConfig",
      "Offset": 18407
    },
    {
      "UniqueName": "Avatar_Mydeimos_00_Skill01_Phase01",
      "TypeId": "TypeId_TurnBasedAbilityConfig",
      "Offset": 2
    },
    {
      "UniqueName": "Avatar_Mydeimos_00_Skill01_Phase02",
      "TypeId": "TypeId_TurnBasedAbilityConfig",
      "Offset": 368
    },
    {
      "UniqueName": "Avatar_Mydeimos_00_Skill02_Phase01",
      "TypeId": "TypeId_TurnBasedAbilityConfig",
      "Offset": 614
    },
    {
      "UniqueName": "Avatar_Mydeimos_00_Skill02_Phase02",
      "TypeId": "TypeId_TurnBasedAbilityConfig",
      "Offset": 920
    },
    {
      "UniqueName": "Avatar_Mydeimos_00_Skill03_EnterReady",
      "TypeId": "TypeId_TurnBasedAbilityConfig",
      "Offset": 1719
    },
    {
      "UniqueName": "Avatar_Mydeimos_00_Skill03_Phase01",
      "TypeId": "TypeId_TurnBasedAbilityConfig",
      "Offset": 2048
    },
    {
      "UniqueName": "Avatar_Mydeimos_00_Skill03_Phase02",
      "TypeId": "TypeId_TurnBasedAbilityConfig",
      "Offset": 2568
    },
    {
      "UniqueName": "Avatar_Mydeimos_00_PassiveSkill01",
      "TypeId": "TypeId_TurnBasedAbilityConfig",
      "Offset": 3162
    },
    {
      "UniqueName": "Avatar_Mydeimos_00_PassiveSkill01_Insert",
      "TypeId": "TypeId_TurnBasedAbilityConfig",
      "Offset": 5961
    },
    {
      "UniqueName": "Avatar_Mydeimos_00_PassiveSkill01_InsertExit",
      "TypeId": "TypeId_TurnBasedAbilityConfig",
      "Offset": 6429
    },
    {
      "UniqueName": "Avatar_Mydeimos_00_Skill21_Ability",
      "TypeId": "TypeId_TurnBasedAbilityConfig",
      "Offset": 7778
    },
    {
      "UniqueName": "Avatar_Mydeimos_00_Skill22_AbilityTarget",
      "TypeId": "TypeId_TurnBasedAbilityConfig",
      "Offset": 8895
    },
    {
      "UniqueName": "Avatar_Mydeimos_00_Skill22_Ability",
      "TypeId": "TypeId_TurnBasedAbilityConfig",
      "Offset": 9150
    },
    {
      "UniqueName": "Avatar_Mydeimos_00_SkillMazeInLevel",
      "TypeId": "TypeId_TurnBasedAbilityConfig",
      "Offset": 12173
    }
  ]
}