{
  "$type": "RPG.GameCore.RtLevelGroupInfo",
  "GroupName": "R03Poi_Group",
  "AreaAnchorName": "LevelArea_P20421_F20421001_G130",
  "SaveType": "Reset",
  "SavedValueCondition": {
    "Conditions": [],
    "Operation": "And"
  },
  "LoadOnInitial": true,
  "ValueSource": {},
  "ConflictIDList": [],
  "IsHoyoGroup": true,
  "HoYoGroupType": "Container",
  "ConflictWhiteList": [],
  "TagContainer": {
    "List": [
      {
        "Tag": "Group.Level.SceneCapture",
        "TagHash": 612855931
      }
    ]
  },
  "AnchorList": [],
  "MonsterList": [],
  "PropList": [
    {
      "PropID": 100,
      "ValueSource": {},
      "CampID": 4,
      "CustomTriggerMap": {},
      "CustomTriggerMapV2": {},
      "StateConfigs": [],
      "DialogueGroups": [],
      "TalkDialogGroupIDList": [],
      "ServerInteractVerificationIDList": [],
      "StageObjectCapture": {
        "BlockAlias": "A201_R03",
        "PrefabAlias": "RoomWater",
        "UseOverridePos": false
      },
      "DialogueTriggerSkipSpecifiedFakeAvatarList": [],
      "CameraCenterEntityList": [],
      "CameraConfig": {},
      "SpawnConfig": {
        "EntitySpawnConfig": {}
      },
      "Name": "Prop1",
      "ID": 300001,
      "PosX": 14.78,
      "PosY": 206.17,
      "PosZ": 318.09
    },
    {
      "PropID": 100,
      "LoadOnInitial": false,
      "IsOverrideInitLevelGraph": true,
      "InitLevelGraph": "Config/Level/DesignerBackup/ShrinkCE/Prop_A201_Poi02.json",
      "ValueSource": {
        "Values": [
          {
            "$type": "RPG.GameCore.SharedString",
            "Value": "130,300001",
            "Key": "Prop1"
          },
          {
            "$type": "RPG.GameCore.SharedString",
            "Value": "130,300003",
            "Key": "UIProp"
          },
          {
            "$type": "RPG.GameCore.SharedString",
            "Value": "130,300002",
            "Key": "Prop2"
          },
          {
            "$type": "RPG.GameCore.SharedString",
            "Value": "130,300004",
            "Key": "Prop3"
          }
        ]
      },
      "Trigger": {
        "Radius": 7,
        "DimX": 1,
        "DimY": 1,
        "DimZ": 1
      },
      "CampID": 4,
      "CustomTriggerMap": {},
      "CustomTriggerMapV2": {},
      "StateConfigs": [],
      "DialogueGroups": [],
      "TalkDialogGroupIDList": [],
      "ServerInteractVerificationIDList": [],
      "DialogueTriggerSkipSpecifiedFakeAvatarList": [],
      "CameraCenterEntityList": [],
      "CameraConfig": {},
      "SpawnConfig": {
        "EntitySpawnConfig": {}
      },
      "Name": "Prop3",
      "ID": 300003,
      "PosX": 15.107,
      "PosY": 204.24,
      "PosZ": 318.234
    },
    {
      "PropID": 100,
      "IsOverrideInitLevelGraph": true,
      "InitLevelGraph": "Config/Level/Props/Chap04/InitLevelGraph_Prop_Chap04_FlowerHeart_01.json",
      "ValueSource": {
        "Values": [
          {
            "$type": "RPG.GameCore.SharedString",
            "Value": "130,300001",
            "Key": "WaterGroup"
          },
          {
            "$type": "RPG.GameCore.SharedString",
            "Value": "130,300004",
            "Key": "DestroyGroup"
          },
          {
            "$type": "RPG.GameCore.SharedString",
            "Value": "130,300005",
            "Key": "WaterGroup1"
          }
        ]
      },
      "CampID": 4,
      "CustomTriggerMap": {},
      "CustomTriggerMapV2": {},
      "StateConfigs": [],
      "DialogueGroups": [],
      "TalkDialogGroupIDList": [],
      "ServerInteractVerificationIDList": [],
      "StageObjectCapture": {
        "BlockAlias": "A201_R03",
        "PrefabAlias": "FlowerHeart",
        "UseOverridePos": false
      },
      "DialogueTriggerSkipSpecifiedFakeAvatarList": [],
      "CameraCenterEntityList": [],
      "CameraConfig": {},
      "SpawnConfig": {
        "EntitySpawnConfig": {}
      },
      "Name": "Prop2",
      "ID": 300002,
      "PosX": 15.03,
      "PosY": 208.61,
      "PosZ": 318.38
    },
    {
      "PropID": 100,
      "ValueSource": {},
      "CampID": 4,
      "CustomTriggerMap": {},
      "CustomTriggerMapV2": {},
      "StateConfigs": [],
      "DialogueGroups": [],
      "TalkDialogGroupIDList": [],
      "ServerInteractVerificationIDList": [],
      "StageObjectCapture": {
        "BlockAlias": "A201_R03",
        "PrefabAlias": "DestroyGroup",
        "UseOverridePos": false
      },
      "DialogueTriggerSkipSpecifiedFakeAvatarList": [],
      "CameraCenterEntityList": [],
      "CameraConfig": {},
      "SpawnConfig": {
        "EntitySpawnConfig": {}
      },
      "Name": "Prop4",
      "ID": 300004
    },
    {
      "PropID": 100,
      "ValueSource": {},
      "CampID": 4,
      "CustomTriggerMap": {},
      "CustomTriggerMapV2": {},
      "StateConfigs": [],
      "DialogueGroups": [],
      "TalkDialogGroupIDList": [],
      "ServerInteractVerificationIDList": [],
      "StageObjectCapture": {
        "BlockAlias": "A201_R03",
        "PrefabAlias": "RoomWaterEff",
        "UseOverridePos": false
      },
      "DialogueTriggerSkipSpecifiedFakeAvatarList": [],
      "CameraCenterEntityList": [],
      "CameraConfig": {},
      "SpawnConfig": {
        "EntitySpawnConfig": {}
      },
      "Name": "Prop5",
      "ID": 300005,
      "PosX": 14.78,
      "PosY": 206.17,
      "PosZ": 318.09
    }
  ],
  "DistrictList": [],
  "WaypointList": [],
  "PathwayList": [],
  "BattleAreaList": [],
  "NPCList": [],
  "CrowdList": [],
  "PedestrianList": [],
  "PedestrianV2List": [],
  "AudienceList": [],
  "SmartObjectList": [],
  "CurveList": [],
  "LittleGameList": []
}