{
  "FloorID": 40131001,
  "NavmapConfigPath": "Config/LevelOutput/Map/MapInfo_P20131_F20131001.json",
  "GroupList": [
    {
      "GroupInstanceInfo": {
        "Name": "DefaultData",
        "ID": 1
      },
      "GroupInfo": {
        "AreaAnchorName": "LevelArea_P40131_F40131001_G1",
        "AnchorList": [
          {
            "Name": "PlayerStart",
            "RotY": 90,
            "ID": 1,
            "PosX": -114.41,
            "PosY": -2.11,
            "PosZ": -94.32
          },
          {
            "Name": "Anchor2",
            "RotY": 90,
            "ID": 2,
            "PosX": -50.78,
            "PosY": -0.11,
            "PosZ": -94.1
          },
          {
            "Name": "Anchor3",
            "RotY": 90,
            "ID": 3,
            "PosX": -108.48,
            "PosY": -2.11,
            "PosZ": -94.29
          },
          {
            "Name": "Anchor4",
            "ID": 4,
            "PosX": -74.39,
            "PosY": -0.11,
            "PosZ": -53.88
          }
        ],
        "MonsterList": [],
        "PropList": [
          {
            "PropID": 3002,
            "IsOverrideInitLevelGraph": true,
            "InitLevelGraph": "Config/Level/Props/Raid/InitLevelGraph_Prop_Raid_CheckPoint_01.json",
            "ValueSource": {},
            "Trigger": {
              "Radius": 1.5,
              "Offset": {
                "Y": 1
              },
              "PointList": []
            },
            "CampID": 4,
            "State": "CheckPointDisable",
            "CustomTriggerMap": {
              "CustomTrigger_Spring": {
                "Radius": 6,
                "Offset": {
                  "Y": 1
                },
                "PointList": [],
                "Server": true
              }
            },
            "CustomTriggerMapV2": {},
            "AnchorGroupID": 1,
            "AnchorID": 2,
            "MappingInfoID": 2102,
            "DialogueGroups": [],
            "TalkDialogGroupIDList": [],
            "ServerInteractVerificationIDList": [],
            "TriggerValidGuest": {},
            "SpawnConfig": {
              "EntitySpawnConfig": {}
            },
            "Name": "Prop2",
            "RotY": 90,
            "ID": 300002,
            "PosX": -53.5,
            "PosY": -0.11,
            "PosZ": -91.69
          },
          {
            "PropID": 3002,
            "IsOverrideInitLevelGraph": true,
            "InitLevelGraph": "Config/Level/Props/Raid/InitLevelGraph_Prop_Raid_CheckPoint_01.json",
            "ValueSource": {},
            "Trigger": {
              "Radius": 1.5,
              "Offset": {
                "Y": 1
              },
              "PointList": []
            },
            "CampID": 4,
            "State": "CheckPointDisable",
            "CustomTriggerMap": {
              "CustomTrigger_Spring": {
                "Radius": 6,
                "Offset": {
                  "Y": 1
                },
                "PointList": [],
                "Server": true
              }
            },
            "CustomTriggerMapV2": {},
            "AnchorGroupID": 1,
            "AnchorID": 3,
            "MappingInfoID": 2102,
            "DialogueGroups": [],
            "TalkDialogGroupIDList": [],
            "ServerInteractVerificationIDList": [],
            "TriggerValidGuest": {},
            "SpawnConfig": {
              "EntitySpawnConfig": {}
            },
            "Name": "Prop1",
            "RotY": 90,
            "ID": 300001,
            "PosX": -107.92,
            "PosY": -2.11,
            "PosZ": -90.67
          }
        ],
        "DistrictList": [],
        "NPCList": [
          {
            "NPCID": 2104,
            "DialogueGroups": [],
            "ServerInteractVerificationIDList": [],
            "BoardShowList": [],
            "TalkDialogGroupIDList": [],
            "DefaultIdleFreeStyleMotionID": 200080000,
            "BornType": "Permanent",
            "InitialHiddenNodeList": [],
            "Name": "NPC1",
            "RotY": 290.2,
            "ID": 400001,
            "PosX": -106.122,
            "PosY": -2.114,
            "PosZ": -95.619
          }
        ]
      }
    },
    {
      "GroupInstanceInfo": {
        "Name": "MonsterArea01",
        "ID": 2
      },
      "GroupInfo": {
        "AreaAnchorName": "LevelArea_P40131_F40131001_G2",
        "AnchorList": [],
        "MonsterList": [
          {
            "NPCMonsterID": 1002040,
            "AIConfig": {
              "AIFile": "Config/ConfigAI/Adventure/NPCMonster/ST_NPCMonster_Master_Chase_MazeSkill.json",
              "PathwayList": [],
              "SlaveConfigList": []
            },
            "AIVariableSource": {},
            "ValueSource": {},
            "CampID": 3,
            "BattleArea": {
              "GroupID": 1,
              "ID": 1
            },
            "EventID": 40131008,
            "BoardShowList": [
              2
            ],
            "TagList": [],
            "SpawnConfig": {
              "EntitySpawnConfig": {}
            },
            "Name": "Monster1",
            "RotY": 180,
            "ID": 200001,
            "PosX": -76.19,
            "PosY": -0.11,
            "PosZ": -82.79
          },
          {
            "NPCMonsterID": 1002040,
            "AIConfig": {
              "AIFile": "Config/ConfigAI/Adventure/NPCMonster/ST_NPCMonster_Master_Chase_MazeSkill.json",
              "PathwayList": [
                {
                  "UseOwnerGroup": true,
                  "UseGroup": 2,
                  "UseID": 1
                }
              ],
              "SlaveConfigList": []
            },
            "AIVariableSource": {},
            "ValueSource": {},
            "CampID": 3,
            "BattleArea": {
              "GroupID": 1,
              "ID": 1
            },
            "EventID": 40131010,
            "BoardShowList": [
              2
            ],
            "TagList": [],
            "SpawnConfig": {
              "EntitySpawnConfig": {}
            },
            "Name": "Monster2",
            "RotY": 160.88,
            "ID": 200002,
            "PosX": -67.54,
            "PosY": -0.11,
            "PosZ": -98.74
          },
          {
            "NPCMonsterID": 1002040,
            "AIConfig": {
              "AIFile": "Config/ConfigAI/Adventure/NPCMonster/ST_NPCMonster_Master_Chase_MazeSkill.json",
              "PathwayList": [
                {
                  "UseOwnerGroup": true,
                  "UseGroup": 2,
                  "UseID": 2
                }
              ],
              "SlaveConfigList": []
            },
            "AIVariableSource": {},
            "ValueSource": {},
            "CampID": 3,
            "BattleArea": {
              "GroupID": 1,
              "ID": 1
            },
            "EventID": 40131008,
            "BoardShowList": [
              2
            ],
            "TagList": [],
            "SpawnConfig": {
              "EntitySpawnConfig": {}
            },
            "Name": "Monster3",
            "RotY": 48.24691,
            "ID": 200003,
            "PosX": -63.692,
            "PosY": -0.111,
            "PosZ": -89.046
          },
          {
            "NPCMonsterID": 1002030,
            "AIConfig": {
              "AIFile": "Config/ConfigAI/Adventure/NPCMonster/ST_NPCMonster_Master_Chase_MazeSkill.json",
              "PathwayList": [
                {
                  "UseOwnerGroup": true,
                  "UseGroup": 2,
                  "UseID": 3
                }
              ],
              "SlaveConfigList": []
            },
            "AIVariableSource": {},
            "ValueSource": {},
            "CampID": 3,
            "BattleArea": {
              "GroupID": 1,
              "ID": 1
            },
            "EventID": 40131009,
            "BoardShowList": [
              2
            ],
            "TagList": [],
            "SpawnConfig": {
              "EntitySpawnConfig": {}
            },
            "Name": "Monster5",
            "RotY": 270,
            "ID": 200005,
            "PosX": -75.12,
            "PosY": -0.11,
            "PosZ": -87.57
          },
          {
            "NPCMonsterID": 1002030,
            "AIConfig": {
              "AIFile": "Config/ConfigAI/Adventure/NPCMonster/ST_NPCMonster_Master_Chase_MazeSkill.json",
              "PathwayList": [],
              "SlaveConfigList": []
            },
            "AIVariableSource": {},
            "ValueSource": {},
            "CampID": 3,
            "BattleArea": {
              "GroupID": 1,
              "ID": 1
            },
            "InitialAnimState": "SpecialStandBy2",
            "EventID": 40131011,
            "BoardShowList": [
              2
            ],
            "TagList": [],
            "SpawnConfig": {
              "EntitySpawnConfig": {}
            },
            "Name": "Monster4",
            "RotY": 337.5583,
            "ID": 200004,
            "PosX": -69.08,
            "PosY": -0.11,
            "PosZ": -88.5
          }
        ],
        "PropList": [
          {
            "PropID": 100,
            "IsOverrideInitLevelGraph": true,
            "InitLevelGraph": "Config/Level/Raid/M301_Raid01/Maze_Chap01_M301_Raid01_CheckKillNum.json",
            "CampID": 4,
            "CustomTriggerMap": {},
            "CustomTriggerMapV2": {},
            "DialogueGroups": [],
            "TalkDialogGroupIDList": [],
            "ServerInteractVerificationIDList": [],
            "CameraCenterEntityList": [],
            "Name": "Prop1",
            "ID": 300001
          },
          {
            "PropID": 100,
            "IsOverrideInitLevelGraph": true,
            "InitLevelGraph": "Config/Level/Raid/M301_Raid01/Maze_Chap01_M301_Raid01_BossCase.json",
            "ValueSource": {
              "Values": [
                {
                  "$type": "RPG.GameCore.SharedString",
                  "Key": "Camera"
                },
                {
                  "$type": "RPG.GameCore.SharedString",
                  "Value": "2,200001",
                  "Key": "NPCID"
                }
              ]
            },
            "CampID": 4,
            "CustomTriggerMap": {},
            "CustomTriggerMapV2": {},
            "DialogueGroups": [],
            "TalkDialogGroupIDList": [],
            "ServerInteractVerificationIDList": [],
            "CameraCenterEntityList": [],
            "Name": "Prop2",
            "ID": 300002,
            "PosX": -78.1,
            "PosY": -0.11,
            "PosZ": -76.2
          },
          {
            "PropID": 100,
            "IsOverrideInitLevelGraph": true,
            "CampID": 4,
            "CustomTriggerMap": {},
            "CustomTriggerMapV2": {},
            "DialogueGroups": [],
            "TalkDialogGroupIDList": [],
            "ServerInteractVerificationIDList": [],
            "CameraCenterEntityList": [],
            "Name": "Prop3",
            "ID": 300003
          },
          {
            "PropID": 100,
            "IsOverrideInitLevelGraph": true,
            "InitLevelGraph": "Config/Level/Maze/MazeExtra/Maze_Prop_ElevatorGoback.json",
            "Trigger": {
              "Shape": "Box",
              "Radius": 1,
              "DimX": 1,
              "DimY": 1,
              "DimZ": 10,
              "PointList": []
            },
            "CampID": 4,
            "CustomTriggerMap": {},
            "CustomTriggerMapV2": {},
            "DialogueGroups": [],
            "TalkDialogGroupIDList": [],
            "ServerInteractVerificationIDList": [],
            "CameraCenterEntityList": [],
            "Name": "Prop4",
            "ID": 300004,
            "PosX": -60.18,
            "PosY": -0.11,
            "PosZ": -94.04
          }
        ],
        "DistrictList": [],
        "NPCList": []
      }
    },
    {
      "GroupInstanceInfo": {
        "Name": "DefaultProp",
        "ID": 6
      },
      "GroupInfo": {
        "AreaAnchorName": "LevelArea_P40131_F40131001_G6",
        "AnchorList": [
          {
            "Name": "North",
            "ID": 1,
            "PosX": 0.00035,
            "PosY": -2.7,
            "PosZ": -94.00024
          },
          {
            "Name": "East",
            "RotY": 90,
            "ID": 2,
            "PosX": 0.00035,
            "PosY": -2.7,
            "PosZ": -94.00024
          },
          {
            "Name": "South",
            "RotY": 180,
            "ID": 3,
            "PosX": 0.00035,
            "PosY": -2.7,
            "PosZ": -94.00024
          },
          {
            "Name": "West",
            "RotY": 270,
            "ID": 4,
            "PosX": 0.00035,
            "PosY": -2.7,
            "PosZ": -94.00024
          }
        ],
        "MonsterList": [],
        "PropList": [
          {
            "PropID": 101004,
            "IsOverrideInitLevelGraph": true,
            "ValueSource": {
              "Values": [
                {
                  "$type": "RPG.GameCore.SharedInt",
                  "Value": 6,
                  "Key": "Maze_Prop_Chap01_IronGate06_GroupID"
                },
                {
                  "$type": "RPG.GameCore.SharedInt",
                  "Value": 300005,
                  "Key": "Maze_Prop_Chap01_IronGate06_PropID"
                },
                {
                  "$type": "RPG.GameCore.SharedInt",
                  "Value": 6,
                  "Key": "Maze_Prop_Chap01_IronGate06Controller_GroupID"
                },
                {
                  "$type": "RPG.GameCore.SharedInt",
                  "Value": 300005,
                  "Key": "Maze_Prop_Chap01_IronGate06Controller_PropID"
                },
                {
                  "$type": "RPG.GameCore.SharedString",
                  "Value": "MazeText_LockedDoor",
                  "Key": "Maze_Chap01_Prop_IronGate06_LockHint"
                }
              ]
            },
            "Trigger": {
              "DimX": 5,
              "DimY": 3,
              "DimZ": 1.6,
              "Offset": {
                "Z": 0.8
              },
              "PointList": []
            },
            "CampID": 4,
            "CustomTriggerMap": {},
            "CustomTriggerMapV2": {},
            "StateConfigs": [],
            "DialogueGroups": [],
            "TalkDialogGroupIDList": [],
            "ServerInteractVerificationIDList": [],
            "DialogueTriggerSkipSpecifiedFakeAvatarList": [],
            "CameraCenterEntityList": [],
            "SpawnConfig": {
              "EntitySpawnConfig": {}
            },
            "Name": "Prop5",
            "RotY": 180,
            "ID": 300005,
            "PosX": -0.01,
            "PosY": -0.46,
            "PosZ": -54.68
          },
          {
            "PropID": 301011,
            "IsOverrideInitLevelGraph": true,
            "InitLevelGraph": "Config/Level/Props/Chap01/InitLevelGraph_Prop_Chap01_RotateBridge_State.json",
            "ValueSource": {
              "Values": [
                {
                  "$type": "RPG.GameCore.SharedString",
                  "Value": "LevelArea_P40131_F40131001_G6,North",
                  "Key": "Bridge_Rotate_North"
                },
                {
                  "$type": "RPG.GameCore.SharedString",
                  "Value": "LevelArea_P40131_F40131001_G6,East",
                  "Key": "Bridge_Rotate_East"
                },
                {
                  "$type": "RPG.GameCore.SharedString",
                  "Value": "LevelArea_P40131_F40131001_G6,South",
                  "Key": "Bridge_Rotate_South"
                },
                {
                  "$type": "RPG.GameCore.SharedString",
                  "Value": "LevelArea_P40131_F40131001_G6,West",
                  "Key": "Bridge_Rotate_West"
                },
                {
                  "$type": "RPG.GameCore.SharedString",
                  "Value": "Mission_9010901,Cam_Bridge3",
                  "Key": "Maze_Chap01_RotateBridge_CamAnchor"
                },
                {
                  "$type": "RPG.GameCore.SharedString",
                  "Value": "6,300010",
                  "Key": "BridgeController_01"
                },
                {
                  "$type": "RPG.GameCore.SharedString",
                  "Value": "6,300009",
                  "Key": "BridgeController_02"
                },
                {
                  "$type": "RPG.GameCore.SharedString",
                  "Value": "6,300035",
                  "Key": "BridgeController_03"
                },
                {
                  "$type": "RPG.GameCore.SharedString",
                  "Value": "6,300001",
                  "Key": "BridgeController_04"
                }
              ]
            },
            "Trigger": {
              "Radius": 1,
              "DimX": 1,
              "DimY": 1,
              "DimZ": 1,
              "PointList": []
            },
            "CampID": 4,
            "State": "BridgeState1",
            "CustomTriggerMap": {},
            "CustomTriggerMapV2": {},
            "StateConfigs": [
              {
                "State": "BridgeState1"
              },
              {
                "State": "BridgeState2",
                "Rotation": 90
              },
              {
                "State": "BridgeState3",
                "Rotation": 180
              },
              {
                "State": "BridgeState4",
                "Rotation": 270
              }
            ],
            "DialogueGroups": [],
            "TalkDialogGroupIDList": [],
            "ServerInteractVerificationIDList": [],
            "StageObjectCapture": {
              "BlockAlias": "Chap01_CloseView_MAZ_M301_MazePart07",
              "PrefabAlias": "Chap01_Grd_WheelGear_01_part01"
            },
            "DialogueTriggerSkipSpecifiedFakeAvatarList": [],
            "CameraCenterEntityList": [],
            "CameraConfig": {},
            "TagOverrideComponents": {},
            "SpawnConfig": {
              "EntitySpawnConfig": {}
            },
            "Name": "Prop6",
            "RotY": 180,
            "ID": 300006,
            "PosX": 0.000309,
            "PosY": -2.7,
            "PosZ": -94
          },
          {
            "PropID": 101012,
            "IsOverrideInitLevelGraph": true,
            "InitLevelGraph": "Config/Level/Props/Chap01/InitLevelGraph_Prop_Chap01_RotateBridge_Controller.json",
            "ValueSource": {
              "Values": [
                {
                  "$type": "RPG.GameCore.SharedString",
                  "Value": "Mission_9010901,Cam_Bridge1",
                  "Key": "Maze_Chap01_RotateBridge_CamAnchor"
                },
                {
                  "$type": "RPG.GameCore.SharedString",
                  "Value": "6,300006",
                  "Key": "Maze_Chap01_RotateBridge_Part01"
                }
              ]
            },
            "CampID": 4,
            "State": "Locked",
            "CustomTriggerMap": {},
            "CustomTriggerMapV2": {},
            "StateConfigs": [],
            "DialogueGroups": [],
            "TalkDialogGroupIDList": [],
            "ServerInteractVerificationIDList": [],
            "DialogueTriggerSkipSpecifiedFakeAvatarList": [],
            "CameraCenterEntityList": [],
            "SpawnConfig": {},
            "Name": "BridgeController01",
            "RotY": 77.5,
            "ID": 300010,
            "PosX": 27.59,
            "PosY": -2.999997,
            "PosZ": -87.23
          },
          {
            "PropID": 101012,
            "IsOverrideInitLevelGraph": true,
            "InitLevelGraph": "Config/Level/Props/Chap01/InitLevelGraph_Prop_Chap01_RotateBridge_Controller.json",
            "ValueSource": {
              "Values": [
                {
                  "$type": "RPG.GameCore.SharedString",
                  "Value": "Mission_9010901,Cam_Bridge2",
                  "Key": "Maze_Chap01_RotateBridge_CamAnchor"
                },
                {
                  "$type": "RPG.GameCore.SharedString",
                  "Value": "6,300006",
                  "Key": "Maze_Chap01_RotateBridge_Part01"
                }
              ]
            },
            "CampID": 4,
            "State": "Locked",
            "CustomTriggerMap": {},
            "CustomTriggerMapV2": {},
            "StateConfigs": [],
            "DialogueGroups": [],
            "TalkDialogGroupIDList": [],
            "ServerInteractVerificationIDList": [],
            "DialogueTriggerSkipSpecifiedFakeAvatarList": [],
            "CameraCenterEntityList": [],
            "SpawnConfig": {},
            "Name": "BridgeController02",
            "RotY": 268.1232,
            "ID": 300009,
            "PosX": 3.6,
            "PosY": -3.000002,
            "PosZ": -122.7
          },
          {
            "PropID": 101001,
            "IsOverrideInitLevelGraph": true,
            "InitLevelGraph": "Config/Level/Props/Chap01/InitLevelGraph_Prop_Chap01_BaseConsole_01A_Control_SimpleDoor.json",
            "ValueSource": {
              "Values": [
                {
                  "$type": "RPG.GameCore.SharedString",
                  "Value": "6,300011",
                  "Key": "Maze_Prop_Chap01_BaseControllSimpleDoor"
                }
              ]
            },
            "CampID": 4,
            "CustomTriggerMap": {},
            "CustomTriggerMapV2": {},
            "StateConfigs": [],
            "DialogueGroups": [],
            "TalkDialogGroupIDList": [],
            "ServerInteractVerificationIDList": [],
            "DialogueTriggerSkipSpecifiedFakeAvatarList": [],
            "CameraCenterEntityList": [],
            "SpawnConfig": {},
            "Name": "BridgeController03",
            "RotY": 180,
            "ID": 300035,
            "PosX": -76.924,
            "PosY": -0.111,
            "PosZ": -46.688
          },
          {
            "PropID": 101012,
            "IsOverrideInitLevelGraph": true,
            "InitLevelGraph": "Config/Level/Props/Chap01/InitLevelGraph_Prop_Chap01_RotateBridge_Controller.json",
            "ValueSource": {
              "Values": [
                {
                  "$type": "RPG.GameCore.SharedString",
                  "Value": "Mission_9010901,Cam_Bridge3",
                  "Key": "Maze_Chap01_RotateBridge_CamAnchor"
                },
                {
                  "$type": "RPG.GameCore.SharedString",
                  "Value": "6,300006",
                  "Key": "Maze_Chap01_RotateBridge_Part01"
                }
              ]
            },
            "CampID": 4,
            "CustomTriggerMap": {},
            "CustomTriggerMapV2": {},
            "StateConfigs": [],
            "DialogueGroups": [],
            "TalkDialogGroupIDList": [],
            "ServerInteractVerificationIDList": [],
            "DialogueTriggerSkipSpecifiedFakeAvatarList": [],
            "CameraCenterEntityList": [],
            "SpawnConfig": {},
            "Name": "BridgeController04",
            "RotY": 71.16293,
            "ID": 300001,
            "PosX": -4.66,
            "PosY": -3,
            "PosZ": -64.972
          },
          {
            "PropID": 101004,
            "IsOverrideInitLevelGraph": true,
            "InitLevelGraph": "Config/Level/Props/Chap01/InitLevelGraph_Prop_Chap01_IronGate_06.json",
            "ValueSource": {
              "Values": [
                {
                  "$type": "RPG.GameCore.SharedString",
                  "Value": "MazeText_LockedDoor",
                  "Key": "Maze_Chap01_Prop_IronGate06_LockHint"
                }
              ]
            },
            "CampID": 4,
            "State": "Open",
            "CustomTriggerMap": {},
            "CustomTriggerMapV2": {},
            "StateConfigs": [],
            "DialogueGroups": [],
            "TalkDialogGroupIDList": [],
            "ServerInteractVerificationIDList": [],
            "DialogueTriggerSkipSpecifiedFakeAvatarList": [],
            "CameraCenterEntityList": [],
            "SpawnConfig": {},
            "Name": "Prop11",
            "RotY": 270,
            "ID": 300011,
            "PosX": -60.789,
            "PosY": -0.042,
            "PosZ": -93.97
          },
          {
            "PropID": 101005,
            "IsOverrideInitLevelGraph": true,
            "ValueSource": {
              "Values": [
                {
                  "$type": "RPG.GameCore.SharedString",
                  "Value": "6,300013",
                  "Key": "Maze_Prop_Chap01_IronGate06Controller_ConfigID"
                },
                {
                  "$type": "RPG.GameCore.SharedString",
                  "Value": "MazeText_LockedDoor",
                  "Key": "Maze_Chap01_Prop_IronGate06_LockHint"
                }
              ]
            },
            "CampID": 4,
            "CustomTriggerMap": {},
            "CustomTriggerMapV2": {},
            "StateConfigs": [],
            "DialogueGroups": [],
            "TalkDialogGroupIDList": [],
            "ServerInteractVerificationIDList": [],
            "DialogueTriggerSkipSpecifiedFakeAvatarList": [],
            "CameraCenterEntityList": [],
            "SpawnConfig": {},
            "Name": "Prop13",
            "ID": 300013,
            "PosX": 0.22,
            "PosY": 1.01,
            "PosZ": -182.63
          },
          {
            "PropID": 301003,
            "IsOverrideInitLevelGraph": true,
            "InitLevelGraph": "Config/Level/Maze/Chapter01/M301/Maze_Chapter_01_M301_Power_Core.json",
            "ValueSource": {},
            "CampID": 4,
            "CustomTriggerMap": {},
            "CustomTriggerMapV2": {},
            "StateConfigs": [],
            "DialogueGroups": [],
            "TalkDialogGroupIDList": [],
            "ServerInteractVerificationIDList": [],
            "StageObjectCapture": {
              "BlockAlias": "Chap01_CloseView_MAZ_M301_MazePart08",
              "PrefabAlias": "Chap01_Prop_PowerMerge_01"
            },
            "DialogueTriggerSkipSpecifiedFakeAvatarList": [],
            "CameraCenterEntityList": [],
            "SpawnConfig": {},
            "Name": "Prop8",
            "ID": 300008,
            "PosX": 0.050011,
            "PosY": 1.007363,
            "PosZ": -193.41,
            "IsDelete": true
          },
          {
            "PropID": 101005,
            "IsOverrideInitLevelGraph": true,
            "ValueSource": {
              "Values": [
                {
                  "$type": "RPG.GameCore.SharedString",
                  "Value": "6,300002",
                  "Key": "Maze_Prop_Chap01_IronGate06Controller_ConfigID"
                },
                {
                  "$type": "RPG.GameCore.SharedString",
                  "Value": "MazeText_LockedDoor",
                  "Key": "Maze_Chap01_Prop_IronGate06_LockHint"
                }
              ]
            },
            "CampID": 4,
            "CustomTriggerMap": {},
            "CustomTriggerMapV2": {},
            "StateConfigs": [],
            "DialogueGroups": [],
            "TalkDialogGroupIDList": [],
            "ServerInteractVerificationIDList": [],
            "DialogueTriggerSkipSpecifiedFakeAvatarList": [],
            "CameraCenterEntityList": [],
            "SpawnConfig": {},
            "Name": "Prop2",
            "RotY": 90,
            "ID": 300002,
            "PosX": -117.48,
            "PosY": -2.11,
            "PosZ": -94.1
          },
          {
            "RotX": 3E-06,
            "PropID": 301002,
            "IsOverrideInitLevelGraph": true,
            "ValueSource": {},
            "CampID": 4,
            "CustomTriggerMap": {},
            "CustomTriggerMapV2": {},
            "StateConfigs": [],
            "DialogueGroups": [],
            "TalkDialogGroupIDList": [],
            "ServerInteractVerificationIDList": [],
            "StageObjectCapture": {
              "BlockAlias": "P3",
              "PrefabAlias": "PowerMerge0"
            },
            "DialogueTriggerSkipSpecifiedFakeAvatarList": [],
            "CameraCenterEntityList": [],
            "SpawnConfig": {},
            "Name": "PowerMerge",
            "ID": 300003,
            "PosY": 0.994,
            "PosZ": -193.473
          },
          {
            "PropID": 100,
            "IsOverrideInitLevelGraph": true,
            "ValueSource": {},
            "Trigger": {
              "Shape": "Box",
              "Radius": 1,
              "DimX": 20,
              "DimY": 1,
              "DimZ": 7,
              "PointList": []
            },
            "CampID": 4,
            "CustomTriggerMap": {},
            "CustomTriggerMapV2": {},
            "StateConfigs": [],
            "DialogueGroups": [],
            "TalkDialogGroupIDList": [],
            "ServerInteractVerificationIDList": [],
            "DialogueTriggerSkipSpecifiedFakeAvatarList": [],
            "CameraCenterEntityList": [],
            "SpawnConfig": {},
            "Name": "Prop7",
            "RotY": 90,
            "ID": 300007,
            "PosX": 0.24,
            "PosY": 1.01,
            "PosZ": -182.42
          },
          {
            "PropID": 100,
            "IsOverrideInitLevelGraph": true,
            "InitLevelGraph": "Config/Level/Raid/M301_Raid01/Maze_Chap01_M301_Raid01_EXOpenDoor.json",
            "ValueSource": {
              "Values": [
                {
                  "$type": "RPG.GameCore.SharedString",
                  "Value": "LevelArea_P40131_F40131001_G6,Camera",
                  "Key": "Camera"
                }
              ]
            },
            "CampID": 4,
            "CustomTriggerMap": {},
            "CustomTriggerMapV2": {},
            "StateConfigs": [],
            "DialogueGroups": [],
            "TalkDialogGroupIDList": [],
            "ServerInteractVerificationIDList": [],
            "DialogueTriggerSkipSpecifiedFakeAvatarList": [],
            "CameraCenterEntityList": [],
            "SpawnConfig": {},
            "Name": "Prop4",
            "ID": 300004
          },
          {
            "PropID": 100,
            "IsOverrideInitLevelGraph": true,
            "InitLevelGraph": "Config/Level/Raid/M301_Raid01/Maze_Chap01_M301_Raid01_EXCloseDoor.json",
            "ValueSource": {
              "Values": [
                {
                  "$type": "RPG.GameCore.SharedString",
                  "Value": "LevelArea_P40131_F40131001_G6,Camera",
                  "Key": "Camera"
                },
                {
                  "$type": "RPG.GameCore.SharedString",
                  "Value": "LevelArea_P40131_F40131001_G6,Camera_Look",
                  "Key": "Camera2"
                }
              ]
            },
            "Trigger": {
              "Shape": "Box",
              "Radius": 1,
              "DimX": 1,
              "DimY": 1,
              "DimZ": 10,
              "PointList": []
            },
            "CampID": 4,
            "CustomTriggerMap": {},
            "CustomTriggerMapV2": {},
            "StateConfigs": [],
            "DialogueGroups": [],
            "TalkDialogGroupIDList": [],
            "ServerInteractVerificationIDList": [],
            "DialogueTriggerSkipSpecifiedFakeAvatarList": [],
            "CameraCenterEntityList": [],
            "SpawnConfig": {
              "EntitySpawnConfig": {}
            },
            "Name": "Prop12",
            "ID": 300012,
            "PosX": -107.36,
            "PosY": -2.11,
            "PosZ": -93.56
          },
          {
            "PropID": 301065,
            "IsOverrideInitLevelGraph": true,
            "ValueSource": {},
            "CampID": 4,
            "CustomTriggerMap": {},
            "CustomTriggerMapV2": {},
            "StateConfigs": [],
            "DialogueGroups": [],
            "TalkDialogGroupIDList": [],
            "ServerInteractVerificationIDList": [],
            "DialogueTriggerSkipSpecifiedFakeAvatarList": [],
            "CameraCenterEntityList": [],
            "SpawnConfig": {},
            "Name": "Prop14",
            "RotY": 90,
            "ID": 300014,
            "PosX": -60.759,
            "PosY": -0.042,
            "PosZ": -90.95
          },
          {
            "PropID": 301065,
            "IsOverrideInitLevelGraph": true,
            "ValueSource": {},
            "CustomTriggerMap": {},
            "CustomTriggerMapV2": {},
            "StateConfigs": [],
            "DialogueGroups": [],
            "TalkDialogGroupIDList": [],
            "ServerInteractVerificationIDList": [],
            "DialogueTriggerSkipSpecifiedFakeAvatarList": [],
            "CameraCenterEntityList": [],
            "SpawnConfig": {},
            "Name": "Prop16",
            "RotY": 90,
            "ID": 300016,
            "PosX": -60.759,
            "PosY": -0.042,
            "PosZ": -96.99
          },
          {
            "Scale": {
              "X": 1.43,
              "Y": 1,
              "Z": 1
            },
            "PropID": 105,
            "LoadOnInitial": false,
            "IsOverrideInitLevelGraph": true,
            "ValueSource": {},
            "CampID": 4,
            "CustomTriggerMap": {},
            "CustomTriggerMapV2": {},
            "StateConfigs": [],
            "DialogueGroups": [],
            "TalkDialogGroupIDList": [],
            "ServerInteractVerificationIDList": [],
            "DialogueTriggerSkipSpecifiedFakeAvatarList": [],
            "CameraCenterEntityList": [],
            "SpawnConfig": {},
            "Name": "Prop15",
            "RotY": 90,
            "ID": 300015,
            "PosX": -26.35,
            "PosY": -3,
            "PosZ": -93.47
          },
          {
            "PropID": 100,
            "IsOverrideInitLevelGraph": true,
            "InitLevelGraph": "Config/Level/Raid/M301_Raid01/Maze_Chap01_M301_Raid01_EXChat01.json",
            "ValueSource": {},
            "Trigger": {
              "Shape": "Box",
              "Radius": 1,
              "DimX": 10,
              "DimY": 1,
              "DimZ": 1,
              "PointList": []
            },
            "CampID": 4,
            "CustomTriggerMap": {},
            "CustomTriggerMapV2": {},
            "StateConfigs": [],
            "DialogueGroups": [],
            "TalkDialogGroupIDList": [],
            "ServerInteractVerificationIDList": [],
            "DialogueTriggerSkipSpecifiedFakeAvatarList": [],
            "CameraCenterEntityList": [],
            "SpawnConfig": {},
            "Name": "Prop17",
            "ID": 300017,
            "PosX": -75.59,
            "PosY": -0.11,
            "PosZ": -58.8
          },
          {
            "PropID": 100,
            "IsOverrideInitLevelGraph": true,
            "InitLevelGraph": "Config/Level/Raid/M301_Raid01/Maze_Chap01_M301_Raid01_StageObjClose3.json",
            "ValueSource": {},
            "CampID": 4,
            "CustomTriggerMap": {},
            "CustomTriggerMapV2": {},
            "StateConfigs": [],
            "DialogueGroups": [],
            "TalkDialogGroupIDList": [],
            "ServerInteractVerificationIDList": [],
            "DialogueTriggerSkipSpecifiedFakeAvatarList": [],
            "CameraCenterEntityList": [],
            "SpawnConfig": {
              "EntitySpawnConfig": {}
            },
            "Name": "Prop18",
            "ID": 300018,
            "PosX": -105.53,
            "PosY": -2.11,
            "PosZ": -94.23
          },
          {
            "PropID": 100,
            "IsOverrideInitLevelGraph": true,
            "ValueSource": {
              "Values": [
                {
                  "$type": "RPG.GameCore.SharedString",
                  "Value": "LevelArea_P40131_F40131001_G6,Camera",
                  "Key": "Camera"
                },
                {
                  "$type": "RPG.GameCore.SharedString",
                  "Value": "LevelArea_P40131_F40131001_G6,Camera_Look",
                  "Key": "Camera2"
                }
              ]
            },
            "Trigger": {
              "Shape": "Box",
              "Radius": 1,
              "DimX": 1,
              "DimY": 1,
              "DimZ": 10,
              "PointList": []
            },
            "CampID": 4,
            "CustomTriggerMap": {},
            "CustomTriggerMapV2": {},
            "StateConfigs": [],
            "DialogueGroups": [],
            "TalkDialogGroupIDList": [],
            "ServerInteractVerificationIDList": [],
            "DialogueTriggerSkipSpecifiedFakeAvatarList": [],
            "CameraCenterEntityList": [],
            "SpawnConfig": {
              "EntitySpawnConfig": {}
            },
            "Name": "Prop19",
            "ID": 300019,
            "PosX": -114.373,
            "PosY": -2.114354,
            "PosZ": -94.1757
          }
        ],
        "DistrictList": [],
        "NPCList": [
          {
            "NPCID": 2107,
            "DialogueGroups": [],
            "ServerInteractVerificationIDList": [],
            "BoardShowList": [],
            "TalkDialogGroupIDList": [],
            "DefaultIdleFreeStyleMotionID": 200090000,
            "BornType": "Permanent",
            "InitialHiddenNodeList": [],
            "DialogueTriggerSkipSpecifiedFakeAvatarList": [],
            "OverrideReplaceMaterialKeyList": [],
            "CameraCenterEntityList": [],
            "Name": "NPC1",
            "ID": 400001,
            "PosX": -0.21,
            "PosY": -3,
            "PosZ": -127.71
          }
        ]
      }
    },
    {
      "GroupInstanceInfo": {
        "Name": "Boss",
        "ID": 7
      },
      "GroupInfo": {
        "AreaAnchorName": "LevelArea_P40131_F40131001_G7",
        "AnchorList": [],
        "MonsterList": [
          {
            "NPCMonsterID": 1002040,
            "AIConfig": {
              "AIFile": "Config/ConfigAI/Adventure/NPCMonster/ST_NPCMonster_Master_Chase_MazeSkill.json",
              "PathwayList": [],
              "SlaveConfigList": []
            },
            "CampID": 3,
            "BattleArea": {
              "GroupID": 1,
              "ID": 1
            },
            "InitialAnimState": "SpecialStandBy1",
            "EventID": 40131008,
            "BoardShowList": [
              2
            ],
            "Name": "Monster4",
            "RotY": 90,
            "ID": 200004,
            "PosX": -68.296,
            "PosY": -0.111,
            "PosZ": -54.641
          },
          {
            "NPCMonsterID": 1002030,
            "AIConfig": {
              "AIFile": "Config/ConfigAI/Adventure/NPCMonster/ST_NPCMonster_Master_Chase_MazeSkill.json",
              "PathwayList": [],
              "SlaveConfigList": []
            },
            "CampID": 3,
            "BattleArea": {
              "GroupID": 1,
              "ID": 1
            },
            "InitialAnimState": "SpecialStandBy2",
            "EventID": 40131009,
            "BoardShowList": [
              2
            ],
            "Name": "Monster5",
            "RotY": 311.96,
            "ID": 200005,
            "PosX": -81.762,
            "PosY": -0.111,
            "PosZ": -50.86
          }
        ],
        "PropList": [
          {
            "PropID": 100,
            "IsOverrideInitLevelGraph": true,
            "Trigger": {
              "Shape": "Box",
              "Radius": 1,
              "DimX": 10,
              "DimY": 1,
              "DimZ": 10,
              "PointList": []
            },
            "CampID": 4,
            "CustomTriggerMap": {},
            "DialogueGroups": [],
            "TalkDialogGroupIDList": [],
            "ServerInteractVerificationIDList": [],
            "Name": "Prop1",
            "ID": 300001,
            "PosX": -32.83,
            "PosY": -3,
            "PosZ": -94.14
          }
        ],
        "DistrictList": [],
        "NPCList": [
          {
            "NPCID": 2108,
            "DialogueGroups": [],
            "ServerInteractVerificationIDList": [],
            "BoardShowList": [],
            "TalkDialogGroupIDList": [],
            "DefaultIdleFreeStyleMotionID": 200130000,
            "BornType": "Permanent",
            "InitialHiddenNodeList": [],
            "Name": "NPC1",
            "RotY": 270,
            "ID": 400001,
            "PosX": -32.61,
            "PosY": -3,
            "PosZ": -94.516
          }
        ]
      }
    },
    {
      "GroupInstanceInfo": {
        "Name": "New Group",
        "ID": 9
      },
      "GroupInfo": {
        "AreaAnchorName": "LevelArea_P40131_F40131001_G9",
        "AnchorList": [],
        "MonsterList": [],
        "PropList": [
          {
            "PropID": 101016,
            "IsOverrideInitLevelGraph": true,
            "InitLevelGraph": "Config/Level/Props/Chap01/InitLevelGraph_Prop_Chap01_Des_MPRevoverBox_01.json",
            "EventID": 10001,
            "CustomTriggerMap": {},
            "DialogueGroups": [],
            "TalkDialogGroupIDList": [],
            "ServerInteractVerificationIDList": [],
            "Name": "Prop2",
            "RotY": 40,
            "ID": 300002,
            "PosX": -83.538,
            "PosY": -0.111,
            "PosZ": -52.253
          },
          {
            "PropID": 101015,
            "IsOverrideInitLevelGraph": true,
            "InitLevelGraph": "Config/Level/Props/Chap01/InitLevelGraph_Prop_Chap01_Des_HPRevoverBox_01.json",
            "EventID": 10002,
            "CustomTriggerMap": {},
            "DialogueGroups": [],
            "TalkDialogGroupIDList": [],
            "ServerInteractVerificationIDList": [],
            "Name": "Prop1",
            "RotY": 40,
            "ID": 300001,
            "PosX": -83.69,
            "PosY": -0.11,
            "PosZ": -52.8
          },
          {
            "PropID": 101015,
            "IsOverrideInitLevelGraph": true,
            "InitLevelGraph": "Config/Level/Props/Chap01/InitLevelGraph_Prop_Chap01_Des_HPRevoverBox_01.json",
            "EventID": 10002,
            "CustomTriggerMap": {},
            "DialogueGroups": [],
            "TalkDialogGroupIDList": [],
            "ServerInteractVerificationIDList": [],
            "Name": "Prop3",
            "RotY": 40,
            "ID": 300003,
            "PosX": -34.741,
            "PosY": -3,
            "PosZ": -83.069
          },
          {
            "PropID": 101016,
            "IsOverrideInitLevelGraph": true,
            "InitLevelGraph": "Config/Level/Props/Chap01/InitLevelGraph_Prop_Chap01_Des_MPRevoverBox_01.json",
            "EventID": 10001,
            "CustomTriggerMap": {},
            "DialogueGroups": [],
            "TalkDialogGroupIDList": [],
            "ServerInteractVerificationIDList": [],
            "Name": "Prop4",
            "RotY": 40,
            "ID": 300004,
            "PosX": -8.95,
            "PosY": -3,
            "PosZ": -131.12
          },
          {
            "PropID": 101015,
            "IsOverrideInitLevelGraph": true,
            "InitLevelGraph": "Config/Level/Props/Chap01/InitLevelGraph_Prop_Chap01_Des_HPRevoverBox_01.json",
            "EventID": 10002,
            "CustomTriggerMap": {},
            "DialogueGroups": [],
            "TalkDialogGroupIDList": [],
            "ServerInteractVerificationIDList": [],
            "Name": "Prop5",
            "RotY": 40,
            "ID": 300005,
            "PosX": 35.043,
            "PosY": 1.007,
            "PosZ": -170.67
          },
          {
            "PropID": 101016,
            "IsOverrideInitLevelGraph": true,
            "InitLevelGraph": "Config/Level/Props/Chap01/InitLevelGraph_Prop_Chap01_Des_MPRevoverBox_01.json",
            "EventID": 10001,
            "CustomTriggerMap": {},
            "DialogueGroups": [],
            "TalkDialogGroupIDList": [],
            "ServerInteractVerificationIDList": [],
            "Name": "Prop6",
            "RotY": 40,
            "ID": 300006,
            "PosX": -98.426,
            "PosY": -2.114,
            "PosZ": -91.363
          },
          {
            "PropID": 101015,
            "IsOverrideInitLevelGraph": true,
            "InitLevelGraph": "Config/Level/Props/Chap01/InitLevelGraph_Prop_Chap01_Des_HPRevoverBox_01.json",
            "EventID": 10002,
            "CustomTriggerMap": {},
            "DialogueGroups": [],
            "TalkDialogGroupIDList": [],
            "ServerInteractVerificationIDList": [],
            "Name": "Prop7",
            "RotY": 40,
            "ID": 300007,
            "PosX": -11.54,
            "PosY": -0.98,
            "PosZ": -228.44
          }
        ],
        "DistrictList": [],
        "NPCList": []
      }
    },
    {
      "GroupInstanceInfo": {
        "Name": "BoxMan",
        "ID": 13
      },
      "GroupInfo": {
        "AreaAnchorName": "LevelArea_P40131_F40131001_G13",
        "AnchorList": [
          {
            "Name": "Anchor1",
            "RotY": 90,
            "ID": 1,
            "PosX": -108.8,
            "PosY": -2.119,
            "PosZ": -93.896
          }
        ],
        "MonsterList": [],
        "PropList": [
          {
            "PropID": 217,
            "IsOverrideInitLevelGraph": true,
            "InitLevelGraph": "Config/Level/Props/Chap01/InitLevelGraph_Prop_Chap01_BoxMan_NoCam.json",
            "ValueSource": {
              "Values": [
                {
                  "$type": "RPG.GameCore.SharedString",
                  "Value": "M101_BoxManCamera,C1",
                  "Key": "BoxMan_Cam"
                },
                {
                  "$type": "RPG.GameCore.SharedString",
                  "Value": "Props/Outputs/Chap01/Chap01_Prop_PuzzlePushBox/Chap01_Prop_PuzzlePushBox_Board00.prefab",
                  "Key": "BoxMan_BoardPath"
                },
                {
                  "$type": "RPG.GameCore.SharedString",
                  "Value": "LevelArea_P40131_F40131001_G13",
                  "Key": "SwitchAnchorArea"
                },
                {
                  "$type": "RPG.GameCore.SharedString",
                  "Value": "Anchor1",
                  "Key": "SwitchAnchor"
                },
                {
                  "$type": "RPG.GameCore.SharedString",
                  "Value": "M101_BoxManCamera,CamAnchor01",
                  "Key": "CamAngleAnchor"
                }
              ]
            },
            "Trigger": {
              "Radius": 20,
              "DimX": 1,
              "DimY": 1,
              "DimZ": 1,
              "PointList": [],
              "Server": true
            },
            "CampID": 4,
            "CustomTriggerMap": {},
            "DialogueGroups": [],
            "TalkDialogGroupIDList": [],
            "ServerInteractVerificationIDList": [
              16
            ],
            "Name": "Origin",
            "RotY": 90,
            "ID": 300020,
            "PosX": -109.1,
            "PosY": -2.114355,
            "PosZ": -88.81
          }
        ],
        "DistrictList": [],
        "NPCList": []
      }
    },
    {
      "GroupInstanceInfo": {
        "Name": "BoxMan",
        "ID": 14
      },
      "GroupInfo": {
        "AreaAnchorName": "LevelArea_P40131_F40131001_G14",
        "AnchorList": [
          {
            "RotZ": 7.4E-05,
            "Name": "Anchor1",
            "RotY": 2.166208,
            "ID": 1,
            "PosX": -74.995,
            "PosY": -0.11,
            "PosZ": -73.585
          }
        ],
        "MonsterList": [],
        "PropList": [
          {
            "PropID": 217,
            "IsOverrideInitLevelGraph": true,
            "InitLevelGraph": "Config/Level/Props/Chap01/InitLevelGraph_Prop_Chap01_BoxMan_NoCam.json",
            "ValueSource": {
              "Values": [
                {
                  "$type": "RPG.GameCore.SharedString",
                  "Value": "M101_BoxManCamera,C1",
                  "Key": "BoxMan_Cam"
                },
                {
                  "$type": "RPG.GameCore.SharedString",
                  "Value": "Props/Outputs/Chap01/Chap01_Prop_PuzzlePushBox/Chap01_Prop_PuzzlePushBox_Board01.prefab",
                  "Key": "BoxMan_BoardPath"
                },
                {
                  "$type": "RPG.GameCore.SharedString",
                  "Value": "LevelArea_P40131_F40131001_G14",
                  "Key": "SwitchAnchorArea"
                },
                {
                  "$type": "RPG.GameCore.SharedString",
                  "Value": "Anchor1",
                  "Key": "SwitchAnchor"
                },
                {
                  "$type": "RPG.GameCore.SharedString",
                  "Key": "CamAngleAnchor"
                }
              ]
            },
            "Trigger": {
              "Radius": 20,
              "DimX": 1,
              "DimY": 1,
              "DimZ": 1,
              "PointList": [],
              "Server": true
            },
            "CampID": 4,
            "CustomTriggerMap": {},
            "DialogueGroups": [],
            "TalkDialogGroupIDList": [],
            "ServerInteractVerificationIDList": [
              16
            ],
            "Name": "Origin",
            "ID": 300020,
            "PosX": -80.15,
            "PosY": -0.111,
            "PosZ": -73.91
          },
          {
            "Scale": {
              "X": 1,
              "Y": 2,
              "Z": 1
            },
            "PropID": 100,
            "IsOverrideInitLevelGraph": true,
            "InitLevelGraph": "Config/Level/Maze/MazeExtra/Maze_Prop_ElevatorGoback.json",
            "Trigger": {
              "Shape": "Box",
              "Radius": 1,
              "DimX": 10,
              "DimY": 1,
              "DimZ": 14,
              "PointList": []
            },
            "CampID": 4,
            "CustomTriggerMap": {},
            "DialogueGroups": [],
            "TalkDialogGroupIDList": [],
            "ServerInteractVerificationIDList": [],
            "Name": "Prop1",
            "ID": 300001,
            "PosX": -75.90001,
            "PosY": -0.110987,
            "PosZ": -66.29998
          }
        ],
        "DistrictList": [],
        "NPCList": []
      }
    },
    {
      "GroupInstanceInfo": {
        "Name": "NPCFinish",
        "ID": 17
      },
      "GroupInfo": {
        "AreaAnchorName": "LevelArea_P40131_F40131001_G17",
        "AnchorList": [],
        "MonsterList": [],
        "PropList": [
          {
            "PropID": 100,
            "IsOverrideInitLevelGraph": true,
            "Trigger": {
              "Radius": 1,
              "DimX": 1,
              "DimY": 1,
              "DimZ": 1,
              "PointList": []
            },
            "CampID": 4,
            "CustomTriggerMap": {},
            "DialogueGroups": [],
            "TalkDialogGroupIDList": [],
            "ServerInteractVerificationIDList": [],
            "Name": "Prop1",
            "ID": 300001,
            "PosX": -33.422,
            "PosY": -3,
            "PosZ": -96.231
          }
        ],
        "DistrictList": [],
        "NPCList": [
          {
            "NPCID": 2104,
            "DialogueGroups": [],
            "ServerInteractVerificationIDList": [],
            "BoardShowList": [],
            "TalkDialogGroupIDList": [],
            "DefaultIdleFreeStyleMotionID": 200080000,
            "InitialHiddenNodeList": [],
            "Name": "NPC1",
            "RotY": 291.2173,
            "ID": 400001,
            "PosX": -32.8,
            "PosY": -3,
            "PosZ": -96.52
          }
        ]
      }
    },
    {
      "GroupInstanceInfo": {
        "Name": "RobotHunt",
        "ID": 18
      },
      "GroupInfo": {
        "AreaAnchorName": "LevelArea_P40131_F40131001_G18",
        "AnchorList": [
          {
            "Name": "Move01",
            "ID": 4,
            "PosX": 36.53,
            "PosY": 2,
            "PosZ": -94.11
          },
          {
            "Name": "Move02",
            "ID": 5,
            "PosX": 83.45,
            "PosY": 2,
            "PosZ": -94.11
          }
        ],
        "MonsterList": [],
        "PropList": [
          {
            "Scale": {
              "X": 1.01,
              "Y": 1.01,
              "Z": 1.01
            },
            "PropID": 100,
            "IsOverrideInitLevelGraph": true,
            "InitLevelGraph": "Config/Level/Maze/MazeExtra/Robot_TreasureHunt_New/Maze_Prop_RaidM301_Robot_Gamplay2.json",
            "ValueSource": {
              "Values": [
                {
                  "$type": "RPG.GameCore.SharedString",
                  "Value": "18,300002",
                  "Key": "LinkConnectClear_M301_01"
                },
                {
                  "$type": "RPG.GameCore.SharedString",
                  "Value": "18,300004",
                  "Key": "RobotHuntChest_M301_01"
                },
                {
                  "$type": "RPG.GameCore.SharedString",
                  "Value": "Maze_Prop_RobotGamePlay_M101_Finish",
                  "Key": "RobotGamePlay_Finish_String"
                },
                {
                  "$type": "RPG.GameCore.SharedString",
                  "Value": "18,300007",
                  "Key": "TargetChestClear_M301_01"
                },
                {
                  "$type": "RPG.GameCore.SharedString",
                  "Value": "RobotGamePlay_Enemy_01",
                  "Key": "RobotGamePlay_Enemy_String"
                }
              ]
            },
            "Trigger": {
              "Radius": 2,
              "DimX": 1,
              "DimY": 1,
              "DimZ": 1,
              "PointList": []
            },
            "CampID": 4,
            "OverrideHintRange": 10,
            "CustomTriggerMap": {},
            "DialogueGroups": [],
            "TalkDialogGroupIDList": [],
            "ServerInteractVerificationIDList": [],
            "Name": "RobotTrigger",
            "RotY": 265.9514,
            "ID": 300001,
            "PosX": -96.84,
            "PosY": -2.11,
            "PosZ": -96.98
          },
          {
            "Scale": {
              "X": 1.01,
              "Y": 1.01,
              "Z": 1.01
            },
            "PropID": 301010,
            "IsOverrideInitLevelGraph": true,
            "InitLevelGraph": "Config/Level/Maze/MazeExtra/Robot_TreasureHunt_New/Maze_Prop_BrokenRobotTutorial.json",
            "Trigger": {
              "Radius": 8,
              "DimX": 1,
              "DimY": 1,
              "DimZ": 1,
              "PointList": []
            },
            "CampID": 4,
            "CustomTriggerMap": {},
            "DialogueGroups": [],
            "TalkDialogGroupIDList": [],
            "ServerInteractVerificationIDList": [],
            "Name": "Robot",
            "RotY": 265.9514,
            "ID": 300002,
            "PosX": -96.84,
            "PosY": -2.11,
            "PosZ": -96.98
          },
          {
            "Scale": {
              "X": 1.01,
              "Y": 1.01,
              "Z": 1.01
            },
            "PropID": 100,
            "IsOverrideInitLevelGraph": true,
            "InitLevelGraph": "Config/Level/Maze/MazeExtra/Robot_TreasureHunt_New/Maze_Prop_RobotConsole_CameraInRaid.json",
            "ValueSource": {
              "Values": [
                {
                  "$type": "RPG.GameCore.SharedString",
                  "Value": "LevelArea_P40131_F40131001_G18,Camera",
                  "Key": "Vcam"
                },
                {
                  "$type": "RPG.GameCore.SharedString",
                  "Value": "18,300002",
                  "Key": "TargetController"
                },
                {
                  "$type": "RPG.GameCore.SharedString",
                  "Value": "Props/Outputs/Chap01/Chap01_Prop_CablePuzzle_01/Chap01_Prop_CablePuzzle_22.prefab",
                  "Key": "LinkGamePerfab"
                },
                {
                  "$type": "RPG.GameCore.SharedString",
                  "Value": "18,300009",
                  "Key": "RobotGamePlay_UP_Prop"
                },
                {
                  "$type": "RPG.GameCore.SharedString",
                  "Value": "MazePuzzle_Drone_Up_01",
                  "Key": "RobotGamePlay_UP_String"
                }
              ]
            },
            "Trigger": {
              "Radius": 2,
              "DimX": 1,
              "DimY": 1,
              "DimZ": 1,
              "PointList": []
            },
            "CampID": 4,
            "State": "TriggerEnable",
            "OverrideHintRange": 20,
            "CustomTriggerMap": {},
            "DialogueGroups": [],
            "TalkDialogGroupIDList": [],
            "ServerInteractVerificationIDList": [],
            "Name": "PuzzleTrigger",
            "RotY": 265.9514,
            "ID": 300003,
            "PosX": -97.202,
            "PosY": -1.344,
            "PosZ": -96.837
          },
          {
            "PropID": 100,
            "IsOverrideInitLevelGraph": true,
            "InitLevelGraph": "Config/Level/Maze/MazeExtra/Robot_TreasureHunt_New/Maze_Prop_Robot_Effect.json",
            "ValueSource": {
              "Values": [
                {
                  "$type": "RPG.GameCore.SharedString",
                  "Value": "Maze_Prop_RobotGamePlay_M301_Finish",
                  "Key": "RobotGamePlay_Finish_String"
                }
              ]
            },
            "CampID": 4,
            "CustomTriggerMap": {},
            "DialogueGroups": [],
            "TalkDialogGroupIDList": [],
            "ServerInteractVerificationIDList": [],
            "Name": "Prop7",
            "ID": 300007,
            "PosX": -78.32,
            "PosY": -0.11,
            "PosZ": -75.35
          },
          {
            "PropID": 100,
            "IsOverrideInitLevelGraph": true,
            "CampID": 4,
            "CustomTriggerMap": {},
            "DialogueGroups": [],
            "TalkDialogGroupIDList": [],
            "ServerInteractVerificationIDList": [],
            "Name": "RobotHuntTutorial",
            "ID": 300005
          },
          {
            "PropID": 211,
            "LoadOnInitial": false,
            "IsOverrideInitLevelGraph": true,
            "InitLevelGraph": "Config/Level/Maze/MazeExtra/Robot_TreasureHunt_New/Maze_Prop_Robot_GamplayIcon.json",
            "ValueSource": {
              "Values": [
                {
                  "$type": "RPG.GameCore.SharedString",
                  "Value": "12,300007",
                  "Key": "TargetChestClear_M301_01"
                }
              ]
            },
            "CampID": 4,
            "CustomTriggerMap": {},
            "MappingInfoID": 10045,
            "DialogueGroups": [],
            "TalkDialogGroupIDList": [],
            "ServerInteractVerificationIDList": [],
            "Name": "Prop6",
            "RotY": 22.61566,
            "ID": 300006
          },
          {
            "PropID": 211,
            "LoadOnInitial": false,
            "IsOverrideInitLevelGraph": true,
            "InitLevelGraph": "Config/Level/Maze/MazeExtra/Robot_TreasureHunt_New/Maze_Prop_Robot_GamplayIcon_Finish.json",
            "ValueSource": {
              "Values": [
                {
                  "$type": "RPG.GameCore.SharedString",
                  "Value": "Maze_Prop_RobotGamePlay_M101_Finish",
                  "Key": "RobotGamePlay_Finish_String"
                },
                {
                  "$type": "RPG.GameCore.SharedString",
                  "Value": "12,300004",
                  "Key": "RobotGamePlay_Chest"
                }
              ]
            },
            "CampID": 4,
            "State": "Open",
            "CustomTriggerMap": {},
            "MappingInfoID": 10045,
            "DialogueGroups": [],
            "TalkDialogGroupIDList": [],
            "ServerInteractVerificationIDList": [],
            "Name": "Prop8",
            "RotY": 270,
            "ID": 300008,
            "PosX": 35.21,
            "PosY": 4.65,
            "PosZ": -102.86
          },
          {
            "PropID": 100,
            "LoadOnInitial": false,
            "IsOverrideInitLevelGraph": true,
            "Trigger": {
              "Radius": 8,
              "DimX": 1,
              "DimY": 1,
              "DimZ": 1,
              "PointList": []
            },
            "CampID": 4,
            "CustomTriggerMap": {},
            "DialogueGroups": [],
            "TalkDialogGroupIDList": [],
            "ServerInteractVerificationIDList": [],
            "Name": "Prop9",
            "RotY": 22.61566,
            "ID": 300009,
            "PosX": 32.3,
            "PosY": -3,
            "PosZ": -106.32
          },
          {
            "PropID": 100,
            "IsOverrideInitLevelGraph": true,
            "CampID": 4,
            "CustomTriggerMap": {},
            "DialogueGroups": [],
            "TalkDialogGroupIDList": [],
            "ServerInteractVerificationIDList": [],
            "Name": "Prop4",
            "ID": 300004,
            "PosX": 31.1,
            "PosY": -3,
            "PosZ": -104.49
          },
          {
            "PropID": 100,
            "IsOverrideInitLevelGraph": true,
            "CampID": 4,
            "CustomTriggerMap": {},
            "DialogueGroups": [],
            "TalkDialogGroupIDList": [],
            "ServerInteractVerificationIDList": [],
            "Name": "Prop10",
            "ID": 300010
          }
        ],
        "DistrictList": [],
        "NPCList": []
      }
    }
  ],
  "DimensionList": [
    {
      "GroupIndexList": [
        0,
        1,
        2,
        3,
        4,
        5,
        6,
        7,
        8
      ],
      "StartAnchorID": 1,
      "ConstValues": [
        {
          "$type": "RPG.GameCore.FloorTargetAgentConfig",
          "AgentType": "Prop",
          "GroupID": 6,
          "InstanceID": 300006,
          "ID": 2,
          "Name": "RotateBridgeProp"
        }
      ],
      "DefaultEnviroProfile": "Stages/Outputs/Chapter01/EnviroProfile/Chap01_CloseView_ADV_Area_M301_01_Foggy.enviroProfile.asset"
    }
  ],
  "GroupInstanceCommonMap": {
    "1": {
      "SaveType": "Permanent",
      "LoadSide": "Server",
      "LoadOnInitial": true
    },
    "2": {
      "SaveType": "Permanent",
      "LoadSide": "Server",
      "LoadOnInitial": true,
      "UnloadCondition": {
        "Conditions": [
          {
            "Type": "SubMission",
            "ID": 407131105
          }
        ]
      }
    },
    "6": {
      "SaveType": "Permanent",
      "LoadSide": "Server",
      "LoadOnInitial": true,
      "GroupRefreshID": 1
    },
    "7": {
      "SaveType": "Permanent",
      "LoadSide": "Server",
      "LoadOnInitial": true
    },
    "9": {
      "SaveType": "Permanent",
      "LoadSide": "Server",
      "LoadOnInitial": true
    },
    "13": {
      "SaveType": "Permanent",
      "LoadSide": "Server"
    },
    "14": {
      "SaveType": "Permanent",
      "LoadSide": "Server",
      "LoadOnInitial": true
    },
    "17": {
      "Category": "Mission",
      "SaveType": "Reset"
    },
    "18": {
      "SaveType": "Permanent",
      "LoadSide": "Server",
      "LoadOnInitial": true
    }
  },
  "LayerToAreaMask": [
    1
  ],
  "StartAnchorID": 1
}