{
  "OnInitSequece": [],
  "OnStartSequece": [
    {
      "TaskList": [
        {
          "$type": "RPG.GameCore.ShowRogueTalkUI",
          "Show": true
        },
        {
          "$type": "RPG.GameCore.ShowRogueTalkBg",
          "TalkBgID": 626101
        },
        {
          "$type": "RPG.GameCore.PlayAndWaitRogueSimpleTalk",
          "SimpleTalkList": [
            {
              "TalkSentenceID": 403817420
            },
            {
              "TalkSentenceID": 403817421
            },
            {
              "TalkSentenceID": 403817422
            },
            {
              "TalkSentenceID": 403817423
            }
          ]
        },
        {
          "$type": "RPG.GameCore.PlayRogueOptionTalk",
          "OptionList": [
            {
              "RogueOptionID": 626101,
              "OptionTextmapID": {
                "Hash": 17104172971060160084
              },
              "OptionIconType": "ChatContinueIcon",
              "TriggerCustomString": "triggerOpt_626101"
            },
            {
              "RogueOptionID": 626102,
              "OptionTextmapID": {
                "Hash": 903730063416421357
              },
              "OptionIconType": "ChatContinueIcon",
              "TriggerCustomString": "triggerOpt_626102"
            },
            {
              "RogueOptionID": 626103,
              "OptionTextmapID": {
                "Hash": 11625800898828575485
              },
              "OptionIconType": "ChatContinueIcon",
              "TriggerCustomString": "triggerOpt_626103"
            },
            {
              "RogueOptionID": 626113,
              "OptionTextmapID": {
                "Hash": 11625800898828575485
              },
              "OptionIconType": "ChatContinueIcon",
              "TriggerCustomString": "ALL_TALK_END"
            }
          ]
        }
      ]
    },
    {
      "TaskList": [
        {
          "$type": "RPG.GameCore.WaitCustomString",
          "CustomString": {
            "Value": "triggerOpt_626101"
          }
        },
        {
          "$type": "RPG.GameCore.PlayAndWaitRogueSimpleTalk",
          "SimpleTalkList": [
            {
              "TalkSentenceID": 403817424
            }
          ]
        },
        {
          "$type": "RPG.GameCore.PlayRogueOptionTalk",
          "OptionList": [
            {
              "RogueOptionID": 626104,
              "OptionTextmapID": {
                "Hash": 13549527845864264714
              },
              "OptionIconType": "ChatContinueIcon",
              "TriggerCustomString": "triggerOpt_626112"
            },
            {
              "RogueOptionID": 626105,
              "OptionTextmapID": {
                "Hash": 5179537749930695153
              },
              "OptionIconType": "ChatContinueIcon",
              "TriggerCustomString": "triggerOpt_626112"
            },
            {
              "RogueOptionID": 626106,
              "OptionTextmapID": {
                "Hash": 16780818501547668278
              },
              "OptionIconType": "ChatContinueIcon",
              "TriggerCustomString": "triggerOpt_626112"
            }
          ]
        }
      ]
    },
    {
      "TaskList": [
        {
          "$type": "RPG.GameCore.WaitCustomString",
          "CustomString": {
            "Value": "triggerOpt_626102"
          }
        },
        {
          "$type": "RPG.GameCore.PlayAndWaitRogueSimpleTalk",
          "SimpleTalkList": [
            {
              "TalkSentenceID": 403817425
            }
          ]
        },
        {
          "$type": "RPG.GameCore.PlayRogueOptionTalk",
          "OptionList": [
            {
              "RogueOptionID": 626107,
              "OptionTextmapID": {
                "Hash": 13919535805556646820
              },
              "OptionIconType": "ChatContinueIcon",
              "TriggerCustomString": "triggerOpt_626112"
            },
            {
              "RogueOptionID": 626108,
              "OptionTextmapID": {
                "Hash": 14968717184693996332
              },
              "OptionIconType": "ChatContinueIcon",
              "TriggerCustomString": "triggerOpt_626112"
            },
            {
              "RogueOptionID": 626109,
              "OptionTextmapID": {
                "Hash": 13409899107977229244
              },
              "OptionIconType": "ChatContinueIcon",
              "TriggerCustomString": "triggerOpt_626112"
            }
          ]
        }
      ]
    },
    {
      "TaskList": [
        {
          "$type": "RPG.GameCore.WaitCustomString",
          "CustomString": {
            "Value": "triggerOpt_626103"
          }
        },
        {
          "$type": "RPG.GameCore.PlayAndWaitRogueSimpleTalk",
          "SimpleTalkList": [
            {
              "TalkSentenceID": 403817426
            }
          ]
        },
        {
          "$type": "RPG.GameCore.PlayRogueOptionTalk",
          "OptionList": [
            {
              "RogueOptionID": 626110,
              "OptionTextmapID": {
                "Hash": 8778712878605855896
              },
              "OptionIconType": "ChatContinueIcon",
              "TriggerCustomString": "triggerOpt_626112"
            },
            {
              "RogueOptionID": 626111,
              "OptionTextmapID": {
                "Hash": 1359645789763574571
              },
              "OptionIconType": "ChatContinueIcon",
              "TriggerCustomString": "triggerOpt_626112"
            },
            {
              "RogueOptionID": 626112,
              "OptionTextmapID": {
                "Hash": 16905921175439334685
              },
              "OptionIconType": "ChatContinueIcon",
              "TriggerCustomString": "triggerOpt_626112"
            }
          ]
        }
      ]
    },
    {
      "TaskList": [
        {
          "$type": "RPG.GameCore.WaitCustomString",
          "CustomString": {
            "Value": "triggerOpt_626112"
          }
        },
        {
          "$type": "RPG.GameCore.PlayAndWaitRogueSimpleTalk",
          "SimpleTalkList": [
            {
              "TalkSentenceID": 403817427
            }
          ]
        },
        {
          "$type": "RPG.GameCore.TriggerCustomString",
          "CustomString": {
            "Value": "ALL_TALK_END"
          }
        }
      ]
    },
    {
      "TaskList": [
        {
          "$type": "RPG.GameCore.WaitCustomString",
          "CustomString": {
            "Value": "ALL_TALK_END"
          }
        },
        {
          "$type": "RPG.GameCore.FinishLevelGraph"
        }
      ]
    }
  ]
}